{
  "lastUpdated": "2026-03-22T19:20:28.347Z",
  "airport": {
    "code": "PVR",
    "icao": "MMPR",
    "name": "Gustavo Díaz Ordaz International Airport",
    "city": "Puerto Vallarta",
    "timezone": "America/Mexico_City"
  },
  "arrivals": [
    {
      "flightNumber": "HU7926",
      "airline": "CHH",
      "airlineCode": "CHH",
      "origin": "Lic. Benito Juarez Int'l",
      "originCode": "MEX",
      "destination": null,
      "destinationCode": null,
      "scheduled": "2026-03-22T12:00:00Z",
      "estimated": "2026-03-22T12:04:06Z",
      "actual": "2026-03-22T12:04:06Z",
      "status": "Landed",
      "terminal": null,
      "gate": null
    },
    {
      "flightNumber": "XB-IJM",
      "airline": "—",
      "airlineCode": "",
      "origin": "Lic. Gustavo Diaz Ordaz Int'l",
      "originCode": "PVR",
      "destination": null,
      "destinationCode": null,
      "scheduled": "2026-03-22T13:44:20Z",
      "estimated": "2026-03-22T13:40:19Z",
      "actual": "2026-03-22T13:40:19Z",
      "status": "Landed",
      "terminal": null,
      "gate": null
    },
    {
      "flightNumber": "VB1166",
      "airline": "VIV",
      "airlineCode": "VIV",
      "origin": "Lic. Benito Juarez Int'l",
      "originCode": "MEX",
      "destination": null,
      "destinationCode": null,
      "scheduled": "2026-03-22T13:50:00Z",
      "estimated": "2026-03-22T13:51:25Z",
      "actual": "2026-03-22T13:51:25Z",
      "status": "Landed",
      "terminal": null,
      "gate": null
    },
    {
      "flightNumber": "VB4342",
      "airline": "VIV",
      "airlineCode": "VIV",
      "origin": "General Mariano Escobedo Int'l",
      "originCode": "MTY",
      "destination": null,
      "destinationCode": null,
      "scheduled": "2026-03-22T13:50:00Z",
      "estimated": "2026-03-22T13:36:00Z",
      "actual": "2026-03-22T13:36:00Z",
      "status": "Landed",
      "terminal": null,
      "gate": null
    },
    {
      "flightNumber": "AM332",
      "airline": "AMX",
      "airlineCode": "AMX",
      "origin": "Lic. Benito Juarez Int'l",
      "originCode": "MEX",
      "destination": null,
      "destinationCode": null,
      "scheduled": "2026-03-22T14:28:00Z",
      "estimated": "2026-03-22T14:53:18Z",
      "actual": "2026-03-22T14:53:18Z",
      "status": "Landed",
      "terminal": null,
      "gate": null
    },
    {
      "flightNumber": "XA-USE",
      "airline": "—",
      "airlineCode": "",
      "origin": "Don Miguel Hidalgo y Costilla Int'l",
      "originCode": "GDL",
      "destination": null,
      "destinationCode": null,
      "scheduled": "2026-03-22T15:24:43Z",
      "estimated": "2026-03-22T15:13:00Z",
      "actual": "2026-03-22T15:13:00Z",
      "status": "Landed",
      "terminal": null,
      "gate": null
    },
    {
      "flightNumber": "G6548",
      "airline": "GXA",
      "airlineCode": "GXA",
      "origin": "Milwaukee Mitchell Intl Airport",
      "originCode": "MKE",
      "destination": null,
      "destinationCode": null,
      "scheduled": "2026-03-22T15:32:00Z",
      "estimated": "2026-03-22T16:32:55Z",
      "actual": "2026-03-22T16:32:55Z",
      "status": "Landed",
      "terminal": null,
      "gate": null
    },
    {
      "flightNumber": "VB7350",
      "airline": "VIV",
      "airlineCode": "VIV",
      "origin": "Mexico City Santa Lucía Airport",
      "originCode": "NLU",
      "destination": null,
      "destinationCode": null,
      "scheduled": "2026-03-22T15:52:00Z",
      "estimated": "2026-03-22T15:48:56Z",
      "actual": "2026-03-22T15:48:56Z",
      "status": "Landed",
      "terminal": null,
      "gate": null
    },
    {
      "flightNumber": "WS2450",
      "airline": "WJA",
      "airlineCode": "WJA",
      "origin": "Winnipeg Int'l",
      "originCode": "YWG",
      "destination": null,
      "destinationCode": null,
      "scheduled": "2026-03-22T15:54:00Z",
      "estimated": "2026-03-22T15:45:54Z",
      "actual": "2026-03-22T15:45:54Z",
      "status": "Landed",
      "terminal": null,
      "gate": null
    },
    {
      "flightNumber": "DL1935",
      "airline": "DAL",
      "airlineCode": "DAL",
      "origin": "Minneapolis/St Paul Intl",
      "originCode": "MSP",
      "destination": null,
      "destinationCode": null,
      "scheduled": "2026-03-22T15:58:00Z",
      "estimated": "2026-03-22T15:55:49Z",
      "actual": "2026-03-22T15:55:49Z",
      "status": "Landed",
      "terminal": null,
      "gate": null
    },
    {
      "flightNumber": "F968",
      "airline": "FFT",
      "airlineCode": "FFT",
      "origin": "Denver Intl",
      "originCode": "DEN",
      "destination": null,
      "destinationCode": null,
      "scheduled": "2026-03-22T16:04:00Z",
      "estimated": "2026-03-22T16:01:26Z",
      "actual": "2026-03-22T16:01:26Z",
      "status": "Landed",
      "terminal": null,
      "gate": null
    },
    {
      "flightNumber": "SEN707",
      "airline": "SEN",
      "airlineCode": "SEN",
      "origin": "Cabo San Lucas Int'l",
      "originCode": "CSW",
      "destination": null,
      "destinationCode": null,
      "scheduled": "2026-03-22T16:20:00Z",
      "estimated": "2026-03-22T16:14:57Z",
      "actual": "2026-03-22T16:14:57Z",
      "status": "Landed",
      "terminal": null,
      "gate": null
    },
    {
      "flightNumber": "VB4340",
      "airline": "VIV",
      "airlineCode": "VIV",
      "origin": "General Mariano Escobedo Int'l",
      "originCode": "MTY",
      "destination": null,
      "destinationCode": null,
      "scheduled": "2026-03-22T16:20:00Z",
      "estimated": "2026-03-22T16:05:16Z",
      "actual": "2026-03-22T16:05:16Z",
      "status": "Landed",
      "terminal": null,
      "gate": null
    },
    {
      "flightNumber": "F82622",
      "airline": "FLE",
      "airlineCode": "FLE",
      "origin": "Toronto Pearson Int'l",
      "originCode": "YYZ",
      "destination": null,
      "destinationCode": null,
      "scheduled": "2026-03-22T16:29:00Z",
      "estimated": "2026-03-22T17:17:05Z",
      "actual": "2026-03-22T17:17:05Z",
      "status": "Landed",
      "terminal": null,
      "gate": null
    },
    {
      "flightNumber": "WN633",
      "airline": "SWA",
      "airlineCode": "SWA",
      "origin": "Austin-Bergstrom Intl",
      "originCode": "AUS",
      "destination": null,
      "destinationCode": null,
      "scheduled": "2026-03-22T16:43:00Z",
      "estimated": "2026-03-22T16:19:14Z",
      "actual": "2026-03-22T16:19:14Z",
      "status": "Landed",
      "terminal": null,
      "gate": null
    },
    {
      "flightNumber": "XA-MLG",
      "airline": "—",
      "airlineCode": "",
      "origin": "Plan de Guadalupe Int'l",
      "originCode": "SLW",
      "destination": null,
      "destinationCode": null,
      "scheduled": "2026-03-22T16:43:49Z",
      "estimated": "2026-03-22T17:29:00Z",
      "actual": "2026-03-22T17:29:00Z",
      "status": "Landed",
      "terminal": null,
      "gate": null
    },
    {
      "flightNumber": "AS1430",
      "airline": "ASA",
      "airlineCode": "ASA",
      "origin": "Los Angeles Intl",
      "originCode": "LAX",
      "destination": null,
      "destinationCode": null,
      "scheduled": "2026-03-22T16:51:00Z",
      "estimated": "2026-03-22T17:31:41Z",
      "actual": "2026-03-22T17:31:41Z",
      "status": "Landed",
      "terminal": null,
      "gate": null
    },
    {
      "flightNumber": "AA1045",
      "airline": "AAL",
      "airlineCode": "AAL",
      "origin": "Dallas-Fort Worth Intl",
      "originCode": "DFW",
      "destination": null,
      "destinationCode": null,
      "scheduled": "2026-03-22T16:52:00Z",
      "estimated": "2026-03-22T16:22:07Z",
      "actual": "2026-03-22T16:22:07Z",
      "status": "Landed",
      "terminal": null,
      "gate": null
    },
    {
      "flightNumber": "WS2614",
      "airline": "WJA",
      "airlineCode": "WJA",
      "origin": "Calgary Int'l",
      "originCode": "YYC",
      "destination": null,
      "destinationCode": null,
      "scheduled": "2026-03-22T16:54:00Z",
      "estimated": "2026-03-22T16:40:11Z",
      "actual": "2026-03-22T16:40:11Z",
      "status": "Landed",
      "terminal": null,
      "gate": null
    },
    {
      "flightNumber": "LET3133",
      "airline": "LET",
      "airlineCode": "LET",
      "origin": "Lic. Adolfo Lopez Mateos Int'l",
      "originCode": "TLC",
      "destination": null,
      "destinationCode": null,
      "scheduled": "2026-03-22T16:57:10Z",
      "estimated": "2026-03-22T16:59:54Z",
      "actual": "2026-03-22T16:59:54Z",
      "status": "Landed",
      "terminal": null,
      "gate": null
    },
    {
      "flightNumber": "DL1901",
      "airline": "DAL",
      "airlineCode": "DAL",
      "origin": "Detroit Metro Wayne Co",
      "originCode": "DTW",
      "destination": null,
      "destinationCode": null,
      "scheduled": "2026-03-22T17:03:00Z",
      "estimated": "2026-03-22T16:45:55Z",
      "actual": "2026-03-22T16:45:55Z",
      "status": "Landed",
      "terminal": null,
      "gate": null
    },
    {
      "flightNumber": "WS2112",
      "airline": "WJA",
      "airlineCode": "WJA",
      "origin": "Edmonton Int'l",
      "originCode": "YEG",
      "destination": null,
      "destinationCode": null,
      "scheduled": "2026-03-22T17:05:00Z",
      "estimated": "2026-03-22T16:48:11Z",
      "actual": "2026-03-22T16:48:11Z",
      "status": "Landed",
      "terminal": null,
      "gate": null
    },
    {
      "flightNumber": "DL1941",
      "airline": "DAL",
      "airlineCode": "DAL",
      "origin": "Hartsfield-Jackson Intl",
      "originCode": "ATL",
      "destination": null,
      "destinationCode": null,
      "scheduled": "2026-03-22T17:10:00Z",
      "estimated": "2026-03-22T17:00:42Z",
      "actual": "2026-03-22T17:00:42Z",
      "status": "Landed",
      "terminal": null,
      "gate": null
    },
    {
      "flightNumber": "WN1298",
      "airline": "SWA",
      "airlineCode": "SWA",
      "origin": "Phoenix Sky Harbor Intl",
      "originCode": "PHX",
      "destination": null,
      "destinationCode": null,
      "scheduled": "2026-03-22T17:12:00Z",
      "estimated": "2026-03-22T17:03:33Z",
      "actual": "2026-03-22T17:03:33Z",
      "status": "Landed",
      "terminal": null,
      "gate": null
    },
    {
      "flightNumber": "C-FGKS",
      "airline": "—",
      "airlineCode": "",
      "origin": "Sarasota/Bradenton Intl",
      "originCode": "SRQ",
      "destination": null,
      "destinationCode": null,
      "scheduled": "2026-03-22T17:17:00Z",
      "estimated": "2026-03-22T18:32:04Z",
      "actual": "2026-03-22T18:32:04Z",
      "status": "Landed",
      "terminal": null,
      "gate": null
    },
    {
      "flightNumber": "AA1676",
      "airline": "AAL",
      "airlineCode": "AAL",
      "origin": "Chicago O'Hare Intl",
      "originCode": "ORD",
      "destination": null,
      "destinationCode": null,
      "scheduled": "2026-03-22T17:17:00Z",
      "estimated": "2026-03-22T17:06:21Z",
      "actual": "2026-03-22T17:06:21Z",
      "status": "Landed",
      "terminal": null,
      "gate": null
    },
    {
      "flightNumber": "LET7360",
      "airline": "LET",
      "airlineCode": "LET",
      "origin": "Dallas Love Fld",
      "originCode": "DAL",
      "destination": null,
      "destinationCode": null,
      "scheduled": "2026-03-22T17:18:00Z",
      "estimated": "2026-03-22T18:08:21Z",
      "actual": "2026-03-22T18:08:21Z",
      "status": "Landed",
      "terminal": null,
      "gate": null
    },
    {
      "flightNumber": "LET6680",
      "airline": "LET",
      "airlineCode": "LET",
      "origin": "Del Norte Int'l",
      "originCode": "NTR",
      "destination": null,
      "destinationCode": null,
      "scheduled": "2026-03-22T17:19:41Z",
      "estimated": "2026-03-22T17:20:39Z",
      "actual": "2026-03-22T17:20:39Z",
      "status": "Landed",
      "terminal": null,
      "gate": null
    },
    {
      "flightNumber": "UA1622",
      "airline": "UAL",
      "airlineCode": "UAL",
      "origin": "Houston Bush Int'ctl",
      "originCode": "IAH",
      "destination": null,
      "destinationCode": null,
      "scheduled": "2026-03-22T17:22:00Z",
      "estimated": "2026-03-22T17:46:09Z",
      "actual": "2026-03-22T17:46:09Z",
      "status": "Landed",
      "terminal": null,
      "gate": null
    },
    {
      "flightNumber": "N487DT",
      "airline": "—",
      "airlineCode": "",
      "origin": "General Heriberto Jara Int'l",
      "originCode": "VER",
      "destination": null,
      "destinationCode": null,
      "scheduled": "2026-03-22T17:23:01Z",
      "estimated": "2026-03-22T17:01:14Z",
      "actual": "2026-03-22T17:14:00Z",
      "status": "Landed",
      "terminal": null,
      "gate": null
    },
    {
      "flightNumber": "XA-PVR",
      "airline": "—",
      "airlineCode": "",
      "origin": "Lic. Gustavo Diaz Ordaz Int'l",
      "originCode": "PVR",
      "destination": null,
      "destinationCode": null,
      "scheduled": "2026-03-22T17:27:18Z",
      "estimated": "2026-03-22T17:23:42Z",
      "actual": "2026-03-22T17:23:42Z",
      "status": "Landed",
      "terminal": null,
      "gate": null
    },
    {
      "flightNumber": "XA-COR",
      "airline": "—",
      "airlineCode": "",
      "origin": "Puerto Vallarta",
      "originCode": "L 20.87952 -105.29601",
      "destination": null,
      "destinationCode": null,
      "scheduled": "2026-03-22T17:32:34Z",
      "estimated": "2026-03-22T17:32:34Z",
      "actual": "2026-03-22T17:32:34Z",
      "status": "Landed",
      "terminal": null,
      "gate": null
    },
    {
      "flightNumber": "AC1349",
      "airline": "ACA",
      "airlineCode": "ACA",
      "origin": "Toronto Pearson Int'l",
      "originCode": "YYZ",
      "destination": null,
      "destinationCode": null,
      "scheduled": "2026-03-22T17:35:00Z",
      "estimated": "2026-03-22T17:40:24Z",
      "actual": "2026-03-22T17:40:24Z",
      "status": "Landed",
      "terminal": null,
      "gate": null
    },
    {
      "flightNumber": "WS2250",
      "airline": "WJA",
      "airlineCode": "WJA",
      "origin": "Calgary Int'l",
      "originCode": "YYC",
      "destination": null,
      "destinationCode": null,
      "scheduled": "2026-03-22T17:36:00Z",
      "estimated": "2026-03-22T17:35:17Z",
      "actual": "2026-03-22T17:35:17Z",
      "status": "Landed",
      "terminal": null,
      "gate": null
    },
    {
      "flightNumber": "XA-RWS",
      "airline": "—",
      "airlineCode": "",
      "origin": "Queretaro Intercontinental Airport",
      "originCode": "QRO",
      "destination": null,
      "destinationCode": null,
      "scheduled": "2026-03-22T17:36:18Z",
      "estimated": "2026-03-22T17:37:00Z",
      "actual": "2026-03-22T17:37:00Z",
      "status": "Landed",
      "terminal": null,
      "gate": null
    },
    {
      "flightNumber": "UA1452",
      "airline": "UAL",
      "airlineCode": "UAL",
      "origin": "Chicago O'Hare Intl",
      "originCode": "ORD",
      "destination": null,
      "destinationCode": null,
      "scheduled": "2026-03-22T17:43:00Z",
      "estimated": "2026-03-22T18:01:50Z",
      "actual": "2026-03-22T18:01:50Z",
      "status": "Landed",
      "terminal": null,
      "gate": null
    },
    {
      "flightNumber": "VB9144",
      "airline": "VIV",
      "airlineCode": "VIV",
      "origin": "Lic. Adolfo Lopez Mateos Int'l",
      "originCode": "TLC",
      "destination": null,
      "destinationCode": null,
      "scheduled": "2026-03-22T17:55:00Z",
      "estimated": "2026-03-22T17:50:24Z",
      "actual": "2026-03-22T17:50:24Z",
      "status": "Landed",
      "terminal": null,
      "gate": null
    },
    {
      "flightNumber": "AA851",
      "airline": "AAL",
      "airlineCode": "AAL",
      "origin": "Phoenix Sky Harbor Intl",
      "originCode": "PHX",
      "destination": null,
      "destinationCode": null,
      "scheduled": "2026-03-22T18:02:00Z",
      "estimated": "2026-03-22T17:48:24Z",
      "actual": "2026-03-22T17:48:24Z",
      "status": "Landed",
      "terminal": null,
      "gate": null
    },
    {
      "flightNumber": "Y47936",
      "airline": "VOI",
      "airlineCode": "VOI",
      "origin": "General Francisco J. Mujica Int'l",
      "originCode": "MLM",
      "destination": null,
      "destinationCode": null,
      "scheduled": "2026-03-22T18:02:00Z",
      "estimated": "2026-03-22T17:43:46Z",
      "actual": "2026-03-22T17:43:46Z",
      "status": "Landed",
      "terminal": null,
      "gate": null
    },
    {
      "flightNumber": "WS2838",
      "airline": "WJA",
      "airlineCode": "WJA",
      "origin": "Quebec/Jean Lesage Int'l",
      "originCode": "YQB",
      "destination": null,
      "destinationCode": null,
      "scheduled": "2026-03-22T18:02:00Z",
      "estimated": "2026-03-22T17:25:25Z",
      "actual": "2026-03-22T17:25:25Z",
      "status": "Landed",
      "terminal": null,
      "gate": null
    },
    {
      "flightNumber": "AM330",
      "airline": "AMX",
      "airlineCode": "AMX",
      "origin": "Lic. Benito Juarez Int'l",
      "originCode": "MEX",
      "destination": null,
      "destinationCode": null,
      "scheduled": "2026-03-22T18:08:00Z",
      "estimated": "2026-03-22T18:22:00Z",
      "actual": "2026-03-22T18:22:00Z",
      "status": "Landed",
      "terminal": null,
      "gate": null
    },
    {
      "flightNumber": "AA13",
      "airline": "AAL",
      "airlineCode": "AAL",
      "origin": "Dallas-Fort Worth Intl",
      "originCode": "DFW",
      "destination": null,
      "destinationCode": null,
      "scheduled": "2026-03-22T18:16:00Z",
      "estimated": "2026-03-22T18:16:00Z",
      "status": "Scheduled",
      "terminal": null,
      "gate": null
    },
    {
      "flightNumber": "WS2974",
      "airline": "WJA",
      "airlineCode": "WJA",
      "origin": "Montreal-Trudeau",
      "originCode": "YUL",
      "destination": null,
      "destinationCode": null,
      "scheduled": "2026-03-22T18:20:00Z",
      "estimated": "2026-03-22T18:24:44Z",
      "actual": "2026-03-22T18:24:44Z",
      "status": "Landed",
      "terminal": null,
      "gate": null
    },
    {
      "flightNumber": "Y4280",
      "airline": "VOI",
      "airlineCode": "VOI",
      "origin": "Lic. Benito Juarez Int'l",
      "originCode": "MEX",
      "destination": null,
      "destinationCode": null,
      "scheduled": "2026-03-22T18:22:00Z",
      "estimated": "2026-03-22T18:27:28Z",
      "actual": "2026-03-22T18:27:28Z",
      "status": "Landed",
      "terminal": null,
      "gate": null
    },
    {
      "flightNumber": "AA2511",
      "airline": "AAL",
      "airlineCode": "AAL",
      "origin": "Dallas-Fort Worth Intl",
      "originCode": "DFW",
      "destination": null,
      "destinationCode": null,
      "scheduled": "2026-03-22T18:31:00Z",
      "estimated": "2026-03-22T19:32:00Z",
      "status": "En Route",
      "terminal": null,
      "gate": null
    },
    {
      "flightNumber": "UA2257",
      "airline": "UAL",
      "airlineCode": "UAL",
      "origin": "Denver Intl",
      "originCode": "DEN",
      "destination": null,
      "destinationCode": null,
      "scheduled": "2026-03-22T18:36:00Z",
      "estimated": "2026-03-22T18:34:50Z",
      "actual": "2026-03-22T18:34:50Z",
      "status": "Landed",
      "terminal": null,
      "gate": null
    },
    {
      "flightNumber": "AS689",
      "airline": "ASA",
      "airlineCode": "ASA",
      "origin": "San Francisco Int'l",
      "originCode": "SFO",
      "destination": null,
      "destinationCode": null,
      "scheduled": "2026-03-22T18:43:00Z",
      "estimated": "2026-03-22T18:42:41Z",
      "actual": "2026-03-22T18:42:41Z",
      "status": "Landed",
      "terminal": null,
      "gate": null
    },
    {
      "flightNumber": "Y41312",
      "airline": "VOI",
      "airlineCode": "VOI",
      "origin": "Don Miguel Hidalgo y Costilla Int'l",
      "originCode": "GDL",
      "destination": null,
      "destinationCode": null,
      "scheduled": "2026-03-22T18:43:20Z",
      "estimated": "2026-03-22T19:04:12Z",
      "actual": "2026-03-22T19:04:12Z",
      "status": "Landed",
      "terminal": null,
      "gate": null
    },
    {
      "flightNumber": "AC999",
      "airline": "ACA",
      "airlineCode": "ACA",
      "origin": "Montreal-Trudeau",
      "originCode": "YUL",
      "destination": null,
      "destinationCode": null,
      "scheduled": "2026-03-22T18:44:00Z",
      "estimated": "2026-03-22T20:05:00Z",
      "status": "En Route",
      "terminal": null,
      "gate": null
    },
    {
      "flightNumber": "N258MR",
      "airline": "—",
      "airlineCode": "",
      "origin": "Lic. Adolfo Lopez Mateos Int'l",
      "originCode": "TLC",
      "destination": null,
      "destinationCode": null,
      "scheduled": "2026-03-22T18:45:24Z",
      "estimated": "2026-03-22T18:50:41Z",
      "actual": "2026-03-22T18:50:41Z",
      "status": "Landed",
      "terminal": null,
      "gate": null
    },
    {
      "flightNumber": "Y45612",
      "airline": "VOI",
      "airlineCode": "VOI",
      "origin": "General Mariano Escobedo Int'l",
      "originCode": "MTY",
      "destination": null,
      "destinationCode": null,
      "scheduled": "2026-03-22T18:47:00Z",
      "estimated": "2026-03-22T18:30:12Z",
      "actual": "2026-03-22T18:30:12Z",
      "status": "Landed",
      "terminal": null,
      "gate": null
    },
    {
      "flightNumber": "AA2587",
      "airline": "AAL",
      "airlineCode": "AAL",
      "origin": "Los Angeles Intl",
      "originCode": "LAX",
      "destination": null,
      "destinationCode": null,
      "scheduled": "2026-03-22T18:49:00Z",
      "estimated": "2026-03-22T19:00:00Z",
      "actual": "2026-03-22T19:00:00Z",
      "status": "Landed",
      "terminal": null,
      "gate": null
    },
    {
      "flightNumber": "N68VP",
      "airline": "—",
      "airlineCode": "",
      "origin": "Tapachula Int'l",
      "originCode": "TAP",
      "destination": null,
      "destinationCode": null,
      "scheduled": "2026-03-22T18:51:00Z",
      "estimated": "2026-03-22T19:37:41Z",
      "status": "En Route",
      "terminal": null,
      "gate": null
    },
    {
      "flightNumber": "WS2606",
      "airline": "WJA",
      "airlineCode": "WJA",
      "origin": "Vancouver Int'l",
      "originCode": "YVR",
      "destination": null,
      "destinationCode": null,
      "scheduled": "2026-03-22T18:56:00Z",
      "estimated": "2026-03-22T18:47:41Z",
      "actual": "2026-03-22T18:47:41Z",
      "status": "Landed",
      "terminal": null,
      "gate": null
    },
    {
      "flightNumber": "AS248",
      "airline": "ASA",
      "airlineCode": "ASA",
      "origin": "John F Kennedy Intl",
      "originCode": "JFK",
      "destination": null,
      "destinationCode": null,
      "scheduled": "2026-03-22T18:57:00Z",
      "estimated": "2026-03-22T18:41:32Z",
      "actual": "2026-03-22T18:41:32Z",
      "status": "Landed",
      "terminal": null,
      "gate": null
    },
    {
      "flightNumber": "WN514",
      "airline": "SWA",
      "airlineCode": "SWA",
      "origin": "Denver Intl",
      "originCode": "DEN",
      "destination": null,
      "destinationCode": null,
      "scheduled": "2026-03-22T18:59:00Z",
      "estimated": "2026-03-22T18:45:42Z",
      "actual": "2026-03-22T18:45:42Z",
      "status": "Landed",
      "terminal": null,
      "gate": null
    },
    {
      "flightNumber": "Y43120",
      "airline": "VOI",
      "airlineCode": "VOI",
      "origin": "General Abelardo L. Rodriguez Int'l",
      "originCode": "TIJ",
      "destination": null,
      "destinationCode": null,
      "scheduled": "2026-03-22T19:07:00Z",
      "estimated": "2026-03-22T19:14:25Z",
      "actual": "2026-03-22T19:14:25Z",
      "status": "Landed",
      "terminal": null,
      "gate": null
    },
    {
      "flightNumber": "VB8032",
      "airline": "VIV",
      "airlineCode": "VIV",
      "origin": "Abraham Gonzalez Int'l",
      "originCode": "CJS",
      "destination": null,
      "destinationCode": null,
      "scheduled": "2026-03-22T19:10:00Z",
      "estimated": "2026-03-22T20:27:00Z",
      "status": "En Route",
      "terminal": null,
      "gate": null
    },
    {
      "flightNumber": "F82800",
      "airline": "FLE",
      "airlineCode": "FLE",
      "origin": "Vancouver Int'l",
      "originCode": "YVR",
      "destination": null,
      "destinationCode": null,
      "scheduled": "2026-03-22T19:18:00Z",
      "estimated": "2026-03-22T19:17:53Z",
      "actual": "2026-03-22T19:17:53Z",
      "status": "Landed",
      "terminal": null,
      "gate": null
    },
    {
      "flightNumber": "UA1212",
      "airline": "UAL",
      "airlineCode": "UAL",
      "origin": "San Francisco Int'l",
      "originCode": "SFO",
      "destination": null,
      "destinationCode": null,
      "scheduled": "2026-03-22T19:19:00Z",
      "estimated": "2026-03-22T19:32:00Z",
      "status": "En Route",
      "terminal": null,
      "gate": null
    },
    {
      "flightNumber": "WS2326",
      "airline": "WJA",
      "airlineCode": "WJA",
      "origin": "CFB Comox (Comox)",
      "originCode": "YQQ",
      "destination": null,
      "destinationCode": null,
      "scheduled": "2026-03-22T19:27:00Z",
      "estimated": "2026-03-22T19:22:15Z",
      "status": "En Route",
      "terminal": null,
      "gate": null
    },
    {
      "flightNumber": "PD771",
      "airline": "POE",
      "airlineCode": "POE",
      "origin": "Toronto Pearson Int'l",
      "originCode": "YYZ",
      "destination": null,
      "destinationCode": null,
      "scheduled": "2026-03-22T19:32:00Z",
      "estimated": "2026-03-23T00:07:00Z",
      "status": "Scheduled",
      "terminal": null,
      "gate": null
    },
    {
      "flightNumber": "WS2036",
      "airline": "WJA",
      "airlineCode": "WJA",
      "origin": "Abbotsford Int'l",
      "originCode": "YXX",
      "destination": null,
      "destinationCode": null,
      "scheduled": "2026-03-22T19:40:00Z",
      "estimated": "2026-03-22T19:34:00Z",
      "status": "En Route",
      "terminal": null,
      "gate": null
    },
    {
      "flightNumber": "WN108",
      "airline": "SWA",
      "airlineCode": "SWA",
      "origin": "William P Hobby",
      "originCode": "HOU",
      "destination": null,
      "destinationCode": null,
      "scheduled": "2026-03-22T19:43:00Z",
      "estimated": "2026-03-22T19:46:00Z",
      "status": "En Route",
      "terminal": null,
      "gate": null
    },
    {
      "flightNumber": "AA3272",
      "airline": "AAL",
      "airlineCode": "AAL",
      "origin": "Phoenix Sky Harbor Intl",
      "originCode": "PHX",
      "destination": null,
      "destinationCode": null,
      "scheduled": "2026-03-22T19:46:00Z",
      "estimated": "2026-03-22T19:21:00Z",
      "status": "En Route",
      "terminal": null,
      "gate": null
    },
    {
      "flightNumber": "Y4560",
      "airline": "VOI",
      "airlineCode": "VOI",
      "origin": "Lic. Adolfo Lopez Mateos Int'l",
      "originCode": "TLC",
      "destination": null,
      "destinationCode": null,
      "scheduled": "2026-03-22T19:50:00Z",
      "estimated": "2026-03-22T19:43:00Z",
      "status": "En Route",
      "terminal": null,
      "gate": null
    },
    {
      "flightNumber": "WS2152",
      "airline": "WJA",
      "airlineCode": "WJA",
      "origin": "Vancouver Int'l",
      "originCode": "YVR",
      "destination": null,
      "destinationCode": null,
      "scheduled": "2026-03-22T19:51:00Z",
      "estimated": "2026-03-22T19:47:00Z",
      "status": "En Route",
      "terminal": null,
      "gate": null
    },
    {
      "flightNumber": "WS2040",
      "airline": "WJA",
      "airlineCode": "WJA",
      "origin": "Victoria Int'l",
      "originCode": "YYJ",
      "destination": null,
      "destinationCode": null,
      "scheduled": "2026-03-22T19:53:00Z",
      "estimated": "2026-03-22T19:59:00Z",
      "status": "En Route",
      "terminal": null,
      "gate": null
    },
    {
      "flightNumber": "AM334",
      "airline": "AMX",
      "airlineCode": "AMX",
      "origin": "Lic. Benito Juarez Int'l",
      "originCode": "MEX",
      "destination": null,
      "destinationCode": null,
      "scheduled": "2026-03-22T20:07:00Z",
      "estimated": "2026-03-22T20:02:00Z",
      "status": "Scheduled",
      "terminal": null,
      "gate": null
    },
    {
      "flightNumber": "DL1948",
      "airline": "DAL",
      "airlineCode": "DAL",
      "origin": "Salt Lake City Intl",
      "originCode": "SLC",
      "destination": null,
      "destinationCode": null,
      "scheduled": "2026-03-22T20:09:00Z",
      "estimated": "2026-03-22T20:42:00Z",
      "status": "En Route",
      "terminal": null,
      "gate": null
    },
    {
      "flightNumber": "AA2051",
      "airline": "AAL",
      "airlineCode": "AAL",
      "origin": "Chicago O'Hare Intl",
      "originCode": "ORD",
      "destination": null,
      "destinationCode": null,
      "scheduled": "2026-03-22T20:19:00Z",
      "estimated": "2026-03-22T20:32:00Z",
      "status": "En Route",
      "terminal": null,
      "gate": null
    },
    {
      "flightNumber": "VB7412",
      "airline": "VIV",
      "airlineCode": "VIV",
      "origin": "Don Miguel Hidalgo y Costilla Int'l",
      "originCode": "GDL",
      "destination": null,
      "destinationCode": null,
      "scheduled": "2026-03-22T20:19:10Z",
      "estimated": "2026-03-22T20:20:10Z",
      "status": "Scheduled",
      "terminal": null,
      "gate": null
    },
    {
      "flightNumber": "UA319",
      "airline": "UAL",
      "airlineCode": "UAL",
      "origin": "Los Angeles Intl",
      "originCode": "LAX",
      "destination": null,
      "destinationCode": null,
      "scheduled": "2026-03-22T20:20:00Z",
      "estimated": "2026-03-22T20:36:00Z",
      "status": "En Route",
      "terminal": null,
      "gate": null
    },
    {
      "flightNumber": "AA2613",
      "airline": "AAL",
      "airlineCode": "AAL",
      "origin": "Dallas-Fort Worth Intl",
      "originCode": "DFW",
      "destination": null,
      "destinationCode": null,
      "scheduled": "2026-03-22T20:21:00Z",
      "estimated": "2026-03-22T20:02:00Z",
      "status": "En Route",
      "terminal": null,
      "gate": null
    },
    {
      "flightNumber": "Y47304",
      "airline": "VOI",
      "airlineCode": "VOI",
      "origin": "Del Bajio Guanajuato Int'l",
      "originCode": "BJX",
      "destination": null,
      "destinationCode": null,
      "scheduled": "2026-03-22T20:27:00Z",
      "estimated": "2026-03-22T20:27:52Z",
      "status": "Scheduled",
      "terminal": null,
      "gate": null
    },
    {
      "flightNumber": "DL1793",
      "airline": "DAL",
      "airlineCode": "DAL",
      "origin": "Los Angeles Intl",
      "originCode": "LAX",
      "destination": null,
      "destinationCode": null,
      "scheduled": "2026-03-22T20:35:00Z",
      "estimated": "2026-03-22T20:47:00Z",
      "status": "En Route",
      "terminal": null,
      "gate": null
    },
    {
      "flightNumber": "TS106",
      "airline": "TSC",
      "airlineCode": "TSC",
      "origin": "Montreal-Trudeau",
      "originCode": "YUL",
      "destination": null,
      "destinationCode": null,
      "scheduled": "2026-03-22T20:50:00Z",
      "estimated": "2026-03-22T21:08:00Z",
      "status": "En Route",
      "terminal": null,
      "gate": null
    },
    {
      "flightNumber": "AS475",
      "airline": "ASA",
      "airlineCode": "ASA",
      "origin": "San Diego Intl",
      "originCode": "SAN",
      "destination": null,
      "destinationCode": null,
      "scheduled": "2026-03-22T20:55:00Z",
      "estimated": "2026-03-22T22:22:00Z",
      "status": "Scheduled",
      "terminal": null,
      "gate": null
    },
    {
      "flightNumber": "Y47506",
      "airline": "VOI",
      "airlineCode": "VOI",
      "origin": "Queretaro Intercontinental Airport",
      "originCode": "QRO",
      "destination": null,
      "destinationCode": null,
      "scheduled": "2026-03-22T21:03:00Z",
      "estimated": "2026-03-22T21:03:46Z",
      "status": "Scheduled",
      "terminal": null,
      "gate": null
    },
    {
      "flightNumber": "WS2214",
      "airline": "WJA",
      "airlineCode": "WJA",
      "origin": "Kelowna Int'l",
      "originCode": "YLW",
      "destination": null,
      "destinationCode": null,
      "scheduled": "2026-03-22T21:08:00Z",
      "estimated": "2026-03-22T21:00:00Z",
      "status": "En Route",
      "terminal": null,
      "gate": null
    },
    {
      "flightNumber": "VB5084",
      "airline": "VIV",
      "airlineCode": "VIV",
      "origin": "General Abelardo L. Rodriguez Int'l",
      "originCode": "TIJ",
      "destination": null,
      "destinationCode": null,
      "scheduled": "2026-03-22T21:19:00Z",
      "estimated": "2026-03-22T21:20:00Z",
      "status": "En Route",
      "terminal": null,
      "gate": null
    },
    {
      "flightNumber": "DL1921",
      "airline": "DAL",
      "airlineCode": "DAL",
      "origin": "Seattle-Tacoma Intl",
      "originCode": "SEA",
      "destination": null,
      "destinationCode": null,
      "scheduled": "2026-03-22T21:19:00Z",
      "estimated": "2026-03-22T21:48:00Z",
      "status": "En Route",
      "terminal": null,
      "gate": null
    },
    {
      "flightNumber": "AC970",
      "airline": "ACA",
      "airlineCode": "ACA",
      "origin": "Vancouver Int'l",
      "originCode": "YVR",
      "destination": null,
      "destinationCode": null,
      "scheduled": "2026-03-22T21:20:00Z",
      "estimated": "2026-03-22T21:10:00Z",
      "status": "En Route",
      "terminal": null,
      "gate": null
    },
    {
      "flightNumber": "WN763",
      "airline": "SWA",
      "airlineCode": "SWA",
      "origin": "John Wayne",
      "originCode": "SNA",
      "destination": null,
      "destinationCode": null,
      "scheduled": "2026-03-22T21:20:00Z",
      "estimated": "2026-03-22T21:17:00Z",
      "status": "En Route",
      "terminal": null,
      "gate": null
    },
    {
      "flightNumber": "WS2240",
      "airline": "WJA",
      "airlineCode": "WJA",
      "origin": "Calgary Int'l",
      "originCode": "YYC",
      "destination": null,
      "destinationCode": null,
      "scheduled": "2026-03-22T21:29:00Z",
      "estimated": "2026-03-22T21:26:00Z",
      "status": "En Route",
      "terminal": null,
      "gate": null
    },
    {
      "flightNumber": "PD793",
      "airline": "POE",
      "airlineCode": "POE",
      "origin": "Ottawa Macdonald-Cartier Int'l",
      "originCode": "YOW",
      "destination": null,
      "destinationCode": null,
      "scheduled": "2026-03-22T21:30:00Z",
      "estimated": "2026-03-22T22:01:00Z",
      "status": "En Route",
      "terminal": null,
      "gate": null
    },
    {
      "flightNumber": "LXJ365",
      "airline": "LXJ",
      "airlineCode": "LXJ",
      "origin": "Brown Fld Muni",
      "originCode": "SDM",
      "destination": null,
      "destinationCode": null,
      "scheduled": "2026-03-22T21:37:00Z",
      "estimated": "2026-03-22T21:54:20Z",
      "status": "En Route",
      "terminal": null,
      "gate": null
    },
    {
      "flightNumber": "5D880",
      "airline": "SLI",
      "airlineCode": "SLI",
      "origin": "Mexico City Santa Lucía Airport",
      "originCode": "NLU",
      "destination": null,
      "destinationCode": null,
      "scheduled": "2026-03-22T21:38:00Z",
      "estimated": "2026-03-22T21:38:00Z",
      "status": "Scheduled",
      "terminal": null,
      "gate": null
    },
    {
      "flightNumber": "Y43122",
      "airline": "VOI",
      "airlineCode": "VOI",
      "origin": "General Abelardo L. Rodriguez Int'l",
      "originCode": "TIJ",
      "destination": null,
      "destinationCode": null,
      "scheduled": "2026-03-22T21:49:00Z",
      "estimated": "2026-03-22T21:49:41Z",
      "status": "Scheduled",
      "terminal": null,
      "gate": null
    },
    {
      "flightNumber": "AS1336",
      "airline": "ASA",
      "airlineCode": "ASA",
      "origin": "Portland Intl",
      "originCode": "PDX",
      "destination": null,
      "destinationCode": null,
      "scheduled": "2026-03-22T22:07:00Z",
      "estimated": "2026-03-22T22:06:00Z",
      "status": "En Route",
      "terminal": null,
      "gate": null
    },
    {
      "flightNumber": "Y41310",
      "airline": "VOI",
      "airlineCode": "VOI",
      "origin": "Don Miguel Hidalgo y Costilla Int'l",
      "originCode": "GDL",
      "destination": null,
      "destinationCode": null,
      "scheduled": "2026-03-22T22:13:20Z",
      "estimated": "2026-03-22T22:15:58Z",
      "status": "Scheduled",
      "terminal": null,
      "gate": null
    },
    {
      "flightNumber": "WS2150",
      "airline": "WJA",
      "airlineCode": "WJA",
      "origin": "Vancouver Int'l",
      "originCode": "YVR",
      "destination": null,
      "destinationCode": null,
      "scheduled": "2026-03-22T22:21:00Z",
      "estimated": "2026-03-22T22:29:00Z",
      "status": "En Route",
      "terminal": null,
      "gate": null
    },
    {
      "flightNumber": "AA3106",
      "airline": "AAL",
      "airlineCode": "AAL",
      "origin": "Phoenix Sky Harbor Intl",
      "originCode": "PHX",
      "destination": null,
      "destinationCode": null,
      "scheduled": "2026-03-22T22:22:00Z",
      "estimated": "2026-03-22T23:38:00Z",
      "status": "Scheduled",
      "terminal": null,
      "gate": null
    },
    {
      "flightNumber": "VB1168",
      "airline": "VIV",
      "airlineCode": "VIV",
      "origin": "Lic. Benito Juarez Int'l",
      "originCode": "MEX",
      "destination": null,
      "destinationCode": null,
      "scheduled": "2026-03-22T22:26:00Z",
      "estimated": "2026-03-22T22:26:44Z",
      "status": "Scheduled",
      "terminal": null,
      "gate": null
    },
    {
      "flightNumber": "Y45614",
      "airline": "VOI",
      "airlineCode": "VOI",
      "origin": "General Mariano Escobedo Int'l",
      "originCode": "MTY",
      "destination": null,
      "destinationCode": null,
      "scheduled": "2026-03-22T22:54:00Z",
      "estimated": "2026-03-22T22:54:38Z",
      "status": "Scheduled",
      "terminal": null,
      "gate": null
    },
    {
      "flightNumber": "Y47434",
      "airline": "VOI",
      "airlineCode": "VOI",
      "origin": "General Rodolfo Sanchez Taboada Int'l",
      "originCode": "MXL",
      "destination": null,
      "destinationCode": null,
      "scheduled": "2026-03-22T23:06:00Z",
      "estimated": "2026-03-22T23:06:43Z",
      "status": "Scheduled",
      "terminal": null,
      "gate": null
    },
    {
      "flightNumber": "VB4344",
      "airline": "VIV",
      "airlineCode": "VIV",
      "origin": "General Mariano Escobedo Int'l",
      "originCode": "MTY",
      "destination": null,
      "destinationCode": null,
      "scheduled": "2026-03-22T23:17:00Z",
      "estimated": "2026-03-22T23:17:10Z",
      "status": "Scheduled",
      "terminal": null,
      "gate": null
    },
    {
      "flightNumber": "WS2602",
      "airline": "WJA",
      "airlineCode": "WJA",
      "origin": "Edmonton Int'l",
      "originCode": "YEG",
      "destination": null,
      "destinationCode": null,
      "scheduled": "2026-03-22T23:30:00Z",
      "estimated": "2026-03-22T23:28:00Z",
      "status": "En Route",
      "terminal": null,
      "gate": null
    },
    {
      "flightNumber": "LXJ609",
      "airline": "LXJ",
      "airlineCode": "LXJ",
      "origin": "Palm Beach Intl",
      "originCode": "PBI",
      "destination": null,
      "destinationCode": null,
      "scheduled": "2026-03-22T23:38:00Z",
      "estimated": "2026-03-22T23:38:00Z",
      "status": "Scheduled",
      "terminal": null,
      "gate": null
    },
    {
      "flightNumber": "AS437",
      "airline": "ASA",
      "airlineCode": "ASA",
      "origin": "Los Angeles Intl",
      "originCode": "LAX",
      "destination": null,
      "destinationCode": null,
      "scheduled": "2026-03-22T23:56:00Z",
      "estimated": "2026-03-23T00:01:55Z",
      "status": "Scheduled",
      "terminal": null,
      "gate": null
    },
    {
      "flightNumber": "VB7122",
      "airline": "VIV",
      "airlineCode": "VIV",
      "origin": "Don Miguel Hidalgo y Costilla Int'l",
      "originCode": "GDL",
      "destination": null,
      "destinationCode": null,
      "scheduled": "2026-03-23T00:08:20Z",
      "estimated": "2026-03-23T00:10:10Z",
      "status": "Scheduled",
      "terminal": null,
      "gate": null
    },
    {
      "flightNumber": "XN1444",
      "airline": "MXA",
      "airlineCode": "MXA",
      "origin": "Mexico City Santa Lucía Airport",
      "originCode": "NLU",
      "destination": null,
      "destinationCode": null,
      "scheduled": "2026-03-23T00:55:00Z",
      "estimated": "2026-03-23T00:55:00Z",
      "status": "Scheduled",
      "terminal": null,
      "gate": null
    },
    {
      "flightNumber": "VB4348",
      "airline": "VIV",
      "airlineCode": "VIV",
      "origin": "General Mariano Escobedo Int'l",
      "originCode": "MTY",
      "destination": null,
      "destinationCode": null,
      "scheduled": "2026-03-23T03:02:00Z",
      "estimated": "2026-03-23T03:02:19Z",
      "status": "Scheduled",
      "terminal": null,
      "gate": null
    },
    {
      "flightNumber": "WS2610",
      "airline": "WJA",
      "airlineCode": "WJA",
      "origin": "Winnipeg Int'l",
      "originCode": "YWG",
      "destination": null,
      "destinationCode": null,
      "scheduled": "2026-03-23T03:22:00Z",
      "estimated": "2026-03-23T03:22:00Z",
      "status": "Scheduled",
      "terminal": null,
      "gate": null
    },
    {
      "flightNumber": "5D340",
      "airline": "SLI",
      "airlineCode": "SLI",
      "origin": "Lic. Benito Juarez Int'l",
      "originCode": "MEX",
      "destination": null,
      "destinationCode": null,
      "scheduled": "2026-03-23T05:19:00Z",
      "estimated": "2026-03-23T05:19:00Z",
      "status": "Scheduled",
      "terminal": null,
      "gate": null
    }
  ],
  "departures": [
    {
      "flightNumber": "5D331",
      "airline": "SLI",
      "airlineCode": "SLI",
      "origin": null,
      "originCode": null,
      "destination": "Lic. Benito Juarez Int'l",
      "destinationCode": "MEX",
      "scheduled": "2026-03-22T12:28:00Z",
      "estimated": "2026-03-22T12:27:24Z",
      "actual": "2026-03-22T12:27:24Z",
      "status": "Departed",
      "terminal": null,
      "gate": null
    },
    {
      "flightNumber": "AA2694",
      "airline": "AAL",
      "airlineCode": "AAL",
      "origin": null,
      "originCode": null,
      "destination": "Dallas-Fort Worth Intl",
      "destinationCode": "DFW",
      "scheduled": "2026-03-22T12:54:00Z",
      "estimated": "2026-03-22T12:46:49Z",
      "actual": "2026-03-22T12:46:49Z",
      "status": "Departed",
      "terminal": null,
      "gate": null
    },
    {
      "flightNumber": "XB-IJM",
      "airline": "—",
      "airlineCode": "",
      "origin": null,
      "originCode": null,
      "destination": "Lic. Gustavo Diaz Ordaz Int'l",
      "destinationCode": "PVR",
      "scheduled": "2026-03-22T13:30:31Z",
      "estimated": "2026-03-22T13:26:30Z",
      "actual": "2026-03-22T13:26:30Z",
      "status": "Departed",
      "terminal": null,
      "gate": null
    },
    {
      "flightNumber": "HU7926",
      "airline": "CHH",
      "airlineCode": "CHH",
      "origin": null,
      "originCode": null,
      "destination": "Beijing Capital Int'l",
      "destinationCode": "PEK",
      "scheduled": "2026-03-22T14:00:00Z",
      "estimated": "2026-03-22T13:34:07Z",
      "actual": "2026-03-22T13:34:07Z",
      "status": "Departed",
      "terminal": null,
      "gate": null
    },
    {
      "flightNumber": "VB1167",
      "airline": "VIV",
      "airlineCode": "VIV",
      "origin": null,
      "originCode": null,
      "destination": "Lic. Benito Juarez Int'l",
      "destinationCode": "MEX",
      "scheduled": "2026-03-22T15:05:00Z",
      "estimated": "2026-03-22T14:59:19Z",
      "actual": "2026-03-22T14:59:19Z",
      "status": "Departed",
      "terminal": null,
      "gate": null
    },
    {
      "flightNumber": "VB4343",
      "airline": "VIV",
      "airlineCode": "VIV",
      "origin": null,
      "originCode": null,
      "destination": "General Mariano Escobedo Int'l",
      "destinationCode": "MTY",
      "scheduled": "2026-03-22T15:10:00Z",
      "estimated": "2026-03-22T15:11:07Z",
      "actual": "2026-03-22T15:11:07Z",
      "status": "Departed",
      "terminal": null,
      "gate": null
    },
    {
      "flightNumber": "AM335",
      "airline": "AMX",
      "airlineCode": "AMX",
      "origin": null,
      "originCode": null,
      "destination": "Lic. Benito Juarez Int'l",
      "destinationCode": "MEX",
      "scheduled": "2026-03-22T15:56:00Z",
      "estimated": "2026-03-22T16:06:52Z",
      "actual": "2026-03-22T16:06:52Z",
      "status": "Departed",
      "terminal": null,
      "gate": null
    },
    {
      "flightNumber": "XA-PVR",
      "airline": "—",
      "airlineCode": "",
      "origin": null,
      "originCode": null,
      "destination": "Lic. Gustavo Diaz Ordaz Int'l",
      "destinationCode": "PVR",
      "scheduled": "2026-03-22T16:00:37Z",
      "estimated": "2026-03-22T15:57:01Z",
      "actual": "2026-03-22T15:57:01Z",
      "status": "Departed",
      "terminal": null,
      "gate": null
    },
    {
      "flightNumber": "XA-COR",
      "airline": "—",
      "airlineCode": "",
      "origin": null,
      "originCode": null,
      "destination": "Puerto Vallarta",
      "destinationCode": "L 20.88105 -105.35434",
      "scheduled": "2026-03-22T16:20:57Z",
      "estimated": "2026-03-22T16:22:11Z",
      "actual": "2026-03-22T16:22:11Z",
      "status": "Departed",
      "terminal": null,
      "gate": null
    },
    {
      "flightNumber": "N431QS",
      "airline": "—",
      "airlineCode": "",
      "origin": null,
      "originCode": null,
      "destination": "Lic. Adolfo Lopez Mateos Int'l",
      "destinationCode": "TLC",
      "scheduled": "2026-03-22T16:24:00Z",
      "estimated": "2026-03-22T16:49:30Z",
      "actual": "2026-03-22T16:49:30Z",
      "status": "Departed",
      "terminal": null,
      "gate": null
    },
    {
      "flightNumber": "XA-USE",
      "airline": "—",
      "airlineCode": "",
      "origin": null,
      "originCode": null,
      "destination": "Don Miguel Hidalgo y Costilla Int'l",
      "destinationCode": "GDL",
      "scheduled": "2026-03-22T16:40:40Z",
      "estimated": "2026-03-22T16:34:32Z",
      "actual": "2026-03-22T16:34:32Z",
      "status": "Departed",
      "terminal": null,
      "gate": null
    },
    {
      "flightNumber": "VB7351",
      "airline": "VIV",
      "airlineCode": "VIV",
      "origin": null,
      "originCode": null,
      "destination": "Mexico City Santa Lucía Airport",
      "destinationCode": "NLU",
      "scheduled": "2026-03-22T17:05:00Z",
      "estimated": "2026-03-22T16:52:58Z",
      "actual": "2026-03-22T16:52:58Z",
      "status": "Departed",
      "terminal": null,
      "gate": null
    },
    {
      "flightNumber": "WS2451",
      "airline": "WJA",
      "airlineCode": "WJA",
      "origin": null,
      "originCode": null,
      "destination": "Winnipeg Int'l",
      "destinationCode": "YWG",
      "scheduled": "2026-03-22T17:10:00Z",
      "estimated": "2026-03-22T17:08:53Z",
      "actual": "2026-03-22T17:08:53Z",
      "status": "Departed",
      "terminal": null,
      "gate": null
    },
    {
      "flightNumber": "SEN708",
      "airline": "SEN",
      "airlineCode": "SEN",
      "origin": null,
      "originCode": null,
      "destination": "Cabo San Lucas Int'l",
      "destinationCode": "CSW",
      "scheduled": "2026-03-22T17:10:00Z",
      "estimated": "2026-03-22T17:01:45Z",
      "actual": "2026-03-22T17:01:45Z",
      "status": "Departed",
      "terminal": null,
      "gate": null
    },
    {
      "flightNumber": "VB4341",
      "airline": "VIV",
      "airlineCode": "VIV",
      "origin": null,
      "originCode": null,
      "destination": "General Mariano Escobedo Int'l",
      "destinationCode": "MTY",
      "scheduled": "2026-03-22T17:30:00Z",
      "estimated": "2026-03-22T17:18:14Z",
      "actual": "2026-03-22T17:18:14Z",
      "status": "Departed",
      "terminal": null,
      "gate": null
    },
    {
      "flightNumber": "N706NG",
      "airline": "—",
      "airlineCode": "",
      "origin": null,
      "originCode": null,
      "destination": "Unknown",
      "destinationCode": "",
      "scheduled": "2026-03-22T17:39:40Z",
      "estimated": "2026-03-22T17:33:05Z",
      "actual": "2026-03-22T17:33:05Z",
      "status": "Departed",
      "terminal": null,
      "gate": null
    },
    {
      "flightNumber": "G6549",
      "airline": "GXA",
      "airlineCode": "GXA",
      "origin": null,
      "originCode": null,
      "destination": "Milwaukee Mitchell Intl Airport",
      "destinationCode": "MKE",
      "scheduled": "2026-03-22T17:42:14Z",
      "estimated": "2026-03-22T17:38:57Z",
      "actual": "2026-03-22T17:38:57Z",
      "status": "Departed",
      "terminal": null,
      "gate": null
    },
    {
      "flightNumber": "N6066L",
      "airline": "—",
      "airlineCode": "",
      "origin": null,
      "originCode": null,
      "destination": "Playa de Oro Int'l",
      "destinationCode": "ZLO",
      "scheduled": "2026-03-22T17:52:57Z",
      "estimated": "2026-03-22T17:44:55Z",
      "actual": "2026-03-22T17:44:55Z",
      "status": "Departed",
      "terminal": null,
      "gate": null
    },
    {
      "flightNumber": "DL1860",
      "airline": "DAL",
      "airlineCode": "DAL",
      "origin": null,
      "originCode": null,
      "destination": "Minneapolis/St Paul Intl",
      "destinationCode": "MSP",
      "scheduled": "2026-03-22T17:55:00Z",
      "estimated": "2026-03-22T17:54:34Z",
      "actual": "2026-03-22T17:54:34Z",
      "status": "Departed",
      "terminal": null,
      "gate": null
    },
    {
      "flightNumber": "WN632",
      "airline": "SWA",
      "airlineCode": "SWA",
      "origin": null,
      "originCode": null,
      "destination": "Austin-Bergstrom Intl",
      "destinationCode": "AUS",
      "scheduled": "2026-03-22T18:00:00Z",
      "estimated": "2026-03-22T17:51:47Z",
      "actual": "2026-03-22T17:51:47Z",
      "status": "Departed",
      "terminal": null,
      "gate": null
    },
    {
      "flightNumber": "F969",
      "airline": "FFT",
      "airlineCode": "FFT",
      "origin": null,
      "originCode": null,
      "destination": "Denver Intl",
      "destinationCode": "DEN",
      "scheduled": "2026-03-22T18:08:00Z",
      "estimated": "2026-03-22T18:06:38Z",
      "actual": "2026-03-22T18:06:38Z",
      "status": "Departed",
      "terminal": null,
      "gate": null
    },
    {
      "flightNumber": "WS2615",
      "airline": "WJA",
      "airlineCode": "WJA",
      "origin": null,
      "originCode": null,
      "destination": "Calgary Int'l",
      "destinationCode": "YYC",
      "scheduled": "2026-03-22T18:10:00Z",
      "estimated": "2026-03-22T18:13:07Z",
      "actual": "2026-03-22T18:13:07Z",
      "status": "Departed",
      "terminal": null,
      "gate": null
    },
    {
      "flightNumber": "AA1045",
      "airline": "AAL",
      "airlineCode": "AAL",
      "origin": null,
      "originCode": null,
      "destination": "Dallas-Fort Worth Intl",
      "destinationCode": "DFW",
      "scheduled": "2026-03-22T18:12:00Z",
      "estimated": "2026-03-22T18:16:03Z",
      "actual": "2026-03-22T18:16:03Z",
      "status": "Departed",
      "terminal": null,
      "gate": null
    },
    {
      "flightNumber": "WS2113",
      "airline": "WJA",
      "airlineCode": "WJA",
      "origin": null,
      "originCode": null,
      "destination": "Edmonton Int'l",
      "destinationCode": "YEG",
      "scheduled": "2026-03-22T18:15:00Z",
      "estimated": "2026-03-22T18:09:48Z",
      "actual": "2026-03-22T18:09:48Z",
      "status": "Departed",
      "terminal": null,
      "gate": null
    },
    {
      "flightNumber": "N273MM",
      "airline": "—",
      "airlineCode": "",
      "origin": null,
      "originCode": null,
      "destination": "Unknown",
      "destinationCode": "",
      "scheduled": "2026-03-22T18:15:52Z",
      "estimated": "2026-03-22T18:11:13Z",
      "actual": "2026-03-22T18:11:13Z",
      "status": "Departed",
      "terminal": null,
      "gate": null
    },
    {
      "flightNumber": "XA-ERO",
      "airline": "—",
      "airlineCode": "",
      "origin": null,
      "originCode": null,
      "destination": "Unknown",
      "destinationCode": "",
      "scheduled": "2026-03-22T18:18:05Z",
      "estimated": "2026-03-22T18:03:35Z",
      "actual": "2026-03-22T18:03:35Z",
      "status": "Departed",
      "terminal": null,
      "gate": null
    },
    {
      "flightNumber": "F82623",
      "airline": "FLE",
      "airlineCode": "FLE",
      "origin": null,
      "originCode": null,
      "destination": "Toronto Pearson Int'l",
      "destinationCode": "YYZ",
      "scheduled": "2026-03-22T18:20:00Z",
      "estimated": "2026-03-22T18:26:13Z",
      "actual": "2026-03-22T18:26:13Z",
      "status": "Departed",
      "terminal": null,
      "gate": null
    },
    {
      "flightNumber": "AS444",
      "airline": "ASA",
      "airlineCode": "ASA",
      "origin": null,
      "originCode": null,
      "destination": "Los Angeles Intl",
      "destinationCode": "LAX",
      "scheduled": "2026-03-22T18:24:00Z",
      "estimated": "2026-03-22T18:52:23Z",
      "actual": "2026-03-22T18:52:23Z",
      "status": "Departed",
      "terminal": null,
      "gate": null
    },
    {
      "flightNumber": "WN1299",
      "airline": "SWA",
      "airlineCode": "SWA",
      "origin": null,
      "originCode": null,
      "destination": "Phoenix Sky Harbor Intl",
      "destinationCode": "PHX",
      "scheduled": "2026-03-22T18:25:00Z",
      "estimated": "2026-03-22T18:18:45Z",
      "actual": "2026-03-22T18:18:45Z",
      "status": "Departed",
      "terminal": null,
      "gate": null
    },
    {
      "flightNumber": "LET3134",
      "airline": "LET",
      "airlineCode": "LET",
      "origin": null,
      "originCode": null,
      "destination": "Unknown",
      "destinationCode": "",
      "scheduled": "2026-03-22T18:39:10Z",
      "estimated": "2026-03-22T18:33:01Z",
      "actual": "2026-03-22T18:33:01Z",
      "status": "Departed",
      "terminal": null,
      "gate": null
    },
    {
      "flightNumber": "DL1902",
      "airline": "DAL",
      "airlineCode": "DAL",
      "origin": null,
      "originCode": null,
      "destination": "Detroit Metro Wayne Co",
      "destinationCode": "DTW",
      "scheduled": "2026-03-22T18:50:00Z",
      "estimated": "2026-03-22T18:44:01Z",
      "actual": "2026-03-22T18:44:01Z",
      "status": "Departed",
      "terminal": null,
      "gate": null
    },
    {
      "flightNumber": "AA2503",
      "airline": "AAL",
      "airlineCode": "AAL",
      "origin": null,
      "originCode": null,
      "destination": "Chicago O'Hare Intl",
      "destinationCode": "ORD",
      "scheduled": "2026-03-22T19:05:00Z",
      "estimated": "2026-03-22T19:05:32Z",
      "actual": "2026-03-22T19:05:32Z",
      "status": "Departed",
      "terminal": null,
      "gate": null
    },
    {
      "flightNumber": "VB9145",
      "airline": "VIV",
      "airlineCode": "VIV",
      "origin": null,
      "originCode": null,
      "destination": "Lic. Adolfo Lopez Mateos Int'l",
      "destinationCode": "TLC",
      "scheduled": "2026-03-22T19:05:00Z",
      "estimated": "2026-03-22T18:56:51Z",
      "actual": "2026-03-22T18:56:51Z",
      "status": "Departed",
      "terminal": null,
      "gate": null
    },
    {
      "flightNumber": "Y47937",
      "airline": "VOI",
      "airlineCode": "VOI",
      "origin": null,
      "originCode": null,
      "destination": "General Francisco J. Mujica Int'l",
      "destinationCode": "MLM",
      "scheduled": "2026-03-22T19:05:00Z",
      "estimated": "2026-03-22T18:46:31Z",
      "actual": "2026-03-22T18:46:31Z",
      "status": "Departed",
      "terminal": null,
      "gate": null
    },
    {
      "flightNumber": "UA1717",
      "airline": "UAL",
      "airlineCode": "UAL",
      "origin": null,
      "originCode": null,
      "destination": "Chicago O'Hare Intl",
      "destinationCode": "ORD",
      "scheduled": "2026-03-22T19:10:00Z",
      "estimated": "2026-03-22T19:09:49Z",
      "actual": "2026-03-22T19:09:49Z",
      "status": "Departed",
      "terminal": null,
      "gate": null
    },
    {
      "flightNumber": "DL1816",
      "airline": "DAL",
      "airlineCode": "DAL",
      "origin": null,
      "originCode": null,
      "destination": "Hartsfield-Jackson Intl",
      "destinationCode": "ATL",
      "scheduled": "2026-03-22T19:15:00Z",
      "estimated": "2026-03-22T18:59:33Z",
      "actual": "2026-03-22T18:59:33Z",
      "status": "Departed",
      "terminal": null,
      "gate": null
    },
    {
      "flightNumber": "WS2975",
      "airline": "WJA",
      "airlineCode": "WJA",
      "origin": null,
      "originCode": null,
      "destination": "Montreal-Trudeau",
      "destinationCode": "YUL",
      "scheduled": "2026-03-22T19:15:00Z",
      "estimated": "2026-03-22T19:15:00Z",
      "status": "Scheduled",
      "terminal": null,
      "gate": null
    },
    {
      "flightNumber": "AA851",
      "airline": "AAL",
      "airlineCode": "AAL",
      "origin": null,
      "originCode": null,
      "destination": "Phoenix Sky Harbor Intl",
      "destinationCode": "PHX",
      "scheduled": "2026-03-22T19:20:00Z",
      "estimated": "2026-03-22T19:18:31Z",
      "actual": "2026-03-22T19:18:31Z",
      "status": "Departed",
      "terminal": null,
      "gate": null
    },
    {
      "flightNumber": "XA-RFB",
      "airline": "—",
      "airlineCode": "",
      "origin": null,
      "originCode": null,
      "destination": "Unknown",
      "destinationCode": "",
      "scheduled": "2026-03-22T19:20:44Z",
      "estimated": "2026-03-22T19:15:10Z",
      "actual": "2026-03-22T19:15:10Z",
      "status": "Departed",
      "terminal": null,
      "gate": null
    },
    {
      "flightNumber": "LET7361",
      "airline": "LET",
      "airlineCode": "LET",
      "origin": null,
      "originCode": null,
      "destination": "Unknown",
      "destinationCode": "",
      "scheduled": "2026-03-22T19:27:27Z",
      "estimated": "2026-03-22T19:11:41Z",
      "actual": "2026-03-22T19:11:41Z",
      "status": "Departed",
      "terminal": null,
      "gate": null
    },
    {
      "flightNumber": "Y4281",
      "airline": "VOI",
      "airlineCode": "VOI",
      "origin": null,
      "originCode": null,
      "destination": "Lic. Benito Juarez Int'l",
      "destinationCode": "MEX",
      "scheduled": "2026-03-22T19:29:00Z",
      "estimated": "2026-03-22T19:29:00Z",
      "status": "Scheduled",
      "terminal": null,
      "gate": null
    },
    {
      "flightNumber": "C-FGKS",
      "airline": "—",
      "airlineCode": "",
      "origin": null,
      "originCode": null,
      "destination": "Hamilton/John C. Munro Int'l",
      "destinationCode": "YHM",
      "scheduled": "2026-03-22T19:34:58Z",
      "estimated": "2026-03-22T19:34:58Z",
      "status": "Scheduled",
      "terminal": null,
      "gate": null
    },
    {
      "flightNumber": "WS2839",
      "airline": "WJA",
      "airlineCode": "WJA",
      "origin": null,
      "originCode": null,
      "destination": "Quebec/Jean Lesage Int'l",
      "destinationCode": "YQB",
      "scheduled": "2026-03-22T19:40:00Z",
      "estimated": "2026-03-22T19:40:00Z",
      "status": "Scheduled",
      "terminal": null,
      "gate": null
    },
    {
      "flightNumber": "Y45613",
      "airline": "VOI",
      "airlineCode": "VOI",
      "origin": null,
      "originCode": null,
      "destination": "General Mariano Escobedo Int'l",
      "destinationCode": "MTY",
      "scheduled": "2026-03-22T19:40:00Z",
      "estimated": "2026-03-22T19:40:00Z",
      "status": "Scheduled",
      "terminal": null,
      "gate": null
    },
    {
      "flightNumber": "AC1348",
      "airline": "ACA",
      "airlineCode": "ACA",
      "origin": null,
      "originCode": null,
      "destination": "Toronto Pearson Int'l",
      "destinationCode": "YYZ",
      "scheduled": "2026-03-22T19:45:00Z",
      "estimated": "2026-03-22T19:43:00Z",
      "status": "Scheduled",
      "terminal": null,
      "gate": null
    },
    {
      "flightNumber": "UA1243",
      "airline": "UAL",
      "airlineCode": "UAL",
      "origin": null,
      "originCode": null,
      "destination": "San Francisco Int'l",
      "destinationCode": "SFO",
      "scheduled": "2026-03-22T19:47:00Z",
      "estimated": "2026-03-22T19:47:00Z",
      "status": "Scheduled",
      "terminal": null,
      "gate": null
    },
    {
      "flightNumber": "Y41311",
      "airline": "VOI",
      "airlineCode": "VOI",
      "origin": null,
      "originCode": null,
      "destination": "Don Miguel Hidalgo y Costilla Int'l",
      "destinationCode": "GDL",
      "scheduled": "2026-03-22T19:48:30Z",
      "estimated": "2026-03-22T19:49:00Z",
      "status": "Scheduled",
      "terminal": null,
      "gate": null
    },
    {
      "flightNumber": "AM333",
      "airline": "AMX",
      "airlineCode": "AMX",
      "origin": null,
      "originCode": null,
      "destination": "Lic. Benito Juarez Int'l",
      "destinationCode": "MEX",
      "scheduled": "2026-03-22T19:50:00Z",
      "estimated": "2026-03-22T19:50:00Z",
      "status": "Scheduled",
      "terminal": null,
      "gate": null
    },
    {
      "flightNumber": "AA2511",
      "airline": "AAL",
      "airlineCode": "AAL",
      "origin": null,
      "originCode": null,
      "destination": "Dallas-Fort Worth Intl",
      "destinationCode": "DFW",
      "scheduled": "2026-03-22T20:00:00Z",
      "estimated": "2026-03-22T20:50:00Z",
      "status": "Scheduled",
      "terminal": null,
      "gate": null
    },
    {
      "flightNumber": "WS2251",
      "airline": "WJA",
      "airlineCode": "WJA",
      "origin": null,
      "originCode": null,
      "destination": "Calgary Int'l",
      "destinationCode": "YYC",
      "scheduled": "2026-03-22T20:05:00Z",
      "estimated": "2026-03-22T20:05:00Z",
      "status": "Scheduled",
      "terminal": null,
      "gate": null
    },
    {
      "flightNumber": "WS2607",
      "airline": "WJA",
      "airlineCode": "WJA",
      "origin": null,
      "originCode": null,
      "destination": "Vancouver Int'l",
      "destinationCode": "YVR",
      "scheduled": "2026-03-22T20:10:00Z",
      "estimated": "2026-03-22T20:10:00Z",
      "status": "Scheduled",
      "terminal": null,
      "gate": null
    },
    {
      "flightNumber": "VB8033",
      "airline": "VIV",
      "airlineCode": "VIV",
      "origin": null,
      "originCode": null,
      "destination": "Abraham Gonzalez Int'l",
      "destinationCode": "CJS",
      "scheduled": "2026-03-22T20:10:00Z",
      "estimated": "2026-03-22T20:10:00Z",
      "status": "Scheduled",
      "terminal": null,
      "gate": null
    },
    {
      "flightNumber": "Y43121",
      "airline": "VOI",
      "airlineCode": "VOI",
      "origin": null,
      "originCode": null,
      "destination": "General Abelardo L. Rodriguez Int'l",
      "destinationCode": "TIJ",
      "scheduled": "2026-03-22T20:11:00Z",
      "estimated": "2026-03-22T20:11:00Z",
      "status": "Scheduled",
      "terminal": null,
      "gate": null
    },
    {
      "flightNumber": "UA296",
      "airline": "UAL",
      "airlineCode": "UAL",
      "origin": null,
      "originCode": null,
      "destination": "Denver Intl",
      "destinationCode": "DEN",
      "scheduled": "2026-03-22T20:18:00Z",
      "estimated": "2026-03-22T20:22:00Z",
      "status": "Scheduled",
      "terminal": null,
      "gate": null
    },
    {
      "flightNumber": "AA2278",
      "airline": "AAL",
      "airlineCode": "AAL",
      "origin": null,
      "originCode": null,
      "destination": "Chicago O'Hare Intl",
      "destinationCode": "ORD",
      "scheduled": "2026-03-22T20:19:00Z",
      "estimated": "2026-03-22T20:29:00Z",
      "status": "Scheduled",
      "terminal": null,
      "gate": null
    },
    {
      "flightNumber": "WN515",
      "airline": "SWA",
      "airlineCode": "SWA",
      "origin": null,
      "originCode": null,
      "destination": "Denver Intl",
      "destinationCode": "DEN",
      "scheduled": "2026-03-22T20:20:00Z",
      "estimated": "2026-03-22T20:25:00Z",
      "status": "Scheduled",
      "terminal": null,
      "gate": null
    },
    {
      "flightNumber": "AS471",
      "airline": "ASA",
      "airlineCode": "ASA",
      "origin": null,
      "originCode": null,
      "destination": "San Diego Intl",
      "destinationCode": "SAN",
      "scheduled": "2026-03-22T20:22:00Z",
      "estimated": "2026-03-22T20:23:00Z",
      "status": "Scheduled",
      "terminal": null,
      "gate": null
    },
    {
      "flightNumber": "F82801",
      "airline": "FLE",
      "airlineCode": "FLE",
      "origin": null,
      "originCode": null,
      "destination": "Vancouver Int'l",
      "destinationCode": "YVR",
      "scheduled": "2026-03-22T20:30:00Z",
      "estimated": "2026-03-22T20:30:00Z",
      "status": "Scheduled",
      "terminal": null,
      "gate": null
    },
    {
      "flightNumber": "WS2327",
      "airline": "WJA",
      "airlineCode": "WJA",
      "origin": null,
      "originCode": null,
      "destination": "CFB Comox (Comox)",
      "destinationCode": "YQQ",
      "scheduled": "2026-03-22T20:40:00Z",
      "estimated": "2026-03-22T20:40:00Z",
      "status": "Scheduled",
      "terminal": null,
      "gate": null
    },
    {
      "flightNumber": "Y4561",
      "airline": "VOI",
      "airlineCode": "VOI",
      "origin": null,
      "originCode": null,
      "destination": "Lic. Adolfo Lopez Mateos Int'l",
      "destinationCode": "TLC",
      "scheduled": "2026-03-22T20:48:00Z",
      "estimated": "2026-03-22T20:48:00Z",
      "status": "Scheduled",
      "terminal": null,
      "gate": null
    },
    {
      "flightNumber": "UA1166",
      "airline": "UAL",
      "airlineCode": "UAL",
      "origin": null,
      "originCode": null,
      "destination": "Houston Bush Int'ctl",
      "destinationCode": "IAH",
      "scheduled": "2026-03-22T20:50:00Z",
      "estimated": "2026-03-22T20:54:00Z",
      "status": "Scheduled",
      "terminal": null,
      "gate": null
    },
    {
      "flightNumber": "WS2037",
      "airline": "WJA",
      "airlineCode": "WJA",
      "origin": null,
      "originCode": null,
      "destination": "Abbotsford Int'l",
      "destinationCode": "YXX",
      "scheduled": "2026-03-22T20:55:00Z",
      "estimated": "2026-03-22T20:55:00Z",
      "status": "Scheduled",
      "terminal": null,
      "gate": null
    },
    {
      "flightNumber": "AS249",
      "airline": "ASA",
      "airlineCode": "ASA",
      "origin": null,
      "originCode": null,
      "destination": "John F Kennedy Intl",
      "destinationCode": "JFK",
      "scheduled": "2026-03-22T21:03:00Z",
      "estimated": "2026-03-22T21:58:00Z",
      "status": "Scheduled",
      "terminal": null,
      "gate": null
    },
    {
      "flightNumber": "AA3272",
      "airline": "AAL",
      "airlineCode": "AAL",
      "origin": null,
      "originCode": null,
      "destination": "Phoenix Sky Harbor Intl",
      "destinationCode": "PHX",
      "scheduled": "2026-03-22T21:05:00Z",
      "estimated": "2026-03-22T21:15:00Z",
      "status": "Scheduled",
      "terminal": null,
      "gate": null
    },
    {
      "flightNumber": "AC998",
      "airline": "ACA",
      "airlineCode": "ACA",
      "origin": null,
      "originCode": null,
      "destination": "Montreal-Trudeau",
      "destinationCode": "YUL",
      "scheduled": "2026-03-22T21:05:00Z",
      "estimated": "2026-03-22T21:34:00Z",
      "status": "Scheduled",
      "terminal": null,
      "gate": null
    },
    {
      "flightNumber": "WS2153",
      "airline": "WJA",
      "airlineCode": "WJA",
      "origin": null,
      "originCode": null,
      "destination": "Vancouver Int'l",
      "destinationCode": "YVR",
      "scheduled": "2026-03-22T21:10:00Z",
      "estimated": "2026-03-22T21:10:00Z",
      "status": "Scheduled",
      "terminal": null,
      "gate": null
    },
    {
      "flightNumber": "WS2041",
      "airline": "WJA",
      "airlineCode": "WJA",
      "origin": null,
      "originCode": null,
      "destination": "Victoria Int'l",
      "destinationCode": "YYJ",
      "scheduled": "2026-03-22T21:15:00Z",
      "estimated": "2026-03-22T21:15:00Z",
      "status": "Scheduled",
      "terminal": null,
      "gate": null
    },
    {
      "flightNumber": "WN764",
      "airline": "SWA",
      "airlineCode": "SWA",
      "origin": null,
      "originCode": null,
      "destination": "John Wayne",
      "destinationCode": "SNA",
      "scheduled": "2026-03-22T21:15:00Z",
      "estimated": "2026-03-22T21:20:00Z",
      "status": "Scheduled",
      "terminal": null,
      "gate": null
    },
    {
      "flightNumber": "PD772",
      "airline": "POE",
      "airlineCode": "POE",
      "origin": null,
      "originCode": null,
      "destination": "Toronto Pearson Int'l",
      "destinationCode": "YYZ",
      "scheduled": "2026-03-22T21:25:00Z",
      "estimated": "2026-03-23T01:10:00Z",
      "status": "Scheduled",
      "terminal": null,
      "gate": null
    },
    {
      "flightNumber": "Y47305",
      "airline": "VOI",
      "airlineCode": "VOI",
      "origin": null,
      "originCode": null,
      "destination": "Del Bajio Guanajuato Int'l",
      "destinationCode": "BJX",
      "scheduled": "2026-03-22T21:26:00Z",
      "estimated": "2026-03-22T21:26:00Z",
      "status": "Scheduled",
      "terminal": null,
      "gate": null
    },
    {
      "flightNumber": "DL1838",
      "airline": "DAL",
      "airlineCode": "DAL",
      "origin": null,
      "originCode": null,
      "destination": "Salt Lake City Intl",
      "destinationCode": "SLC",
      "scheduled": "2026-03-22T21:39:00Z",
      "estimated": "2026-03-22T21:39:00Z",
      "status": "Scheduled",
      "terminal": null,
      "gate": null
    },
    {
      "flightNumber": "VB7413",
      "airline": "VIV",
      "airlineCode": "VIV",
      "origin": null,
      "originCode": null,
      "destination": "Don Miguel Hidalgo y Costilla Int'l",
      "destinationCode": "GDL",
      "scheduled": "2026-03-22T21:40:00Z",
      "estimated": "2026-03-22T21:40:00Z",
      "status": "Scheduled",
      "terminal": null,
      "gate": null
    },
    {
      "flightNumber": "LXJ486",
      "airline": "LXJ",
      "airlineCode": "LXJ",
      "origin": null,
      "originCode": null,
      "destination": "Scottsdale",
      "destinationCode": "SCF",
      "scheduled": "2026-03-22T21:41:58Z",
      "estimated": "2026-03-22T22:24:00Z",
      "status": "Scheduled",
      "terminal": null,
      "gate": null
    },
    {
      "flightNumber": "AM337",
      "airline": "AMX",
      "airlineCode": "AMX",
      "origin": null,
      "originCode": null,
      "destination": "Lic. Benito Juarez Int'l",
      "destinationCode": "MEX",
      "scheduled": "2026-03-22T21:43:00Z",
      "estimated": "2026-03-22T21:43:00Z",
      "status": "Scheduled",
      "terminal": null,
      "gate": null
    },
    {
      "flightNumber": "AA2613",
      "airline": "AAL",
      "airlineCode": "AAL",
      "origin": null,
      "originCode": null,
      "destination": "Dallas-Fort Worth Intl",
      "destinationCode": "DFW",
      "scheduled": "2026-03-22T21:45:00Z",
      "estimated": "2026-03-22T21:56:00Z",
      "status": "Scheduled",
      "terminal": null,
      "gate": null
    },
    {
      "flightNumber": "UA244",
      "airline": "UAL",
      "airlineCode": "UAL",
      "origin": null,
      "originCode": null,
      "destination": "Los Angeles Intl",
      "destinationCode": "LAX",
      "scheduled": "2026-03-22T21:53:00Z",
      "estimated": "2026-03-22T21:53:00Z",
      "status": "Scheduled",
      "terminal": null,
      "gate": null
    },
    {
      "flightNumber": "AA1881",
      "airline": "AAL",
      "airlineCode": "AAL",
      "origin": null,
      "originCode": null,
      "destination": "Los Angeles Intl",
      "destinationCode": "LAX",
      "scheduled": "2026-03-22T22:01:00Z",
      "estimated": "2026-03-22T22:11:00Z",
      "status": "Scheduled",
      "terminal": null,
      "gate": null
    },
    {
      "flightNumber": "Y47507",
      "airline": "VOI",
      "airlineCode": "VOI",
      "origin": null,
      "originCode": null,
      "destination": "Queretaro Intercontinental Airport",
      "destinationCode": "QRO",
      "scheduled": "2026-03-22T22:04:00Z",
      "estimated": "2026-03-22T22:04:00Z",
      "status": "Scheduled",
      "terminal": null,
      "gate": null
    },
    {
      "flightNumber": "DL1779",
      "airline": "DAL",
      "airlineCode": "DAL",
      "origin": null,
      "originCode": null,
      "destination": "Los Angeles Intl",
      "destinationCode": "LAX",
      "scheduled": "2026-03-22T22:07:00Z",
      "estimated": "2026-03-22T22:07:00Z",
      "status": "Scheduled",
      "terminal": null,
      "gate": null
    },
    {
      "flightNumber": "VB5085",
      "airline": "VIV",
      "airlineCode": "VIV",
      "origin": null,
      "originCode": null,
      "destination": "General Abelardo L. Rodriguez Int'l",
      "destinationCode": "TIJ",
      "scheduled": "2026-03-22T22:20:00Z",
      "estimated": "2026-03-22T22:20:00Z",
      "status": "Scheduled",
      "terminal": null,
      "gate": null
    },
    {
      "flightNumber": "AS1337",
      "airline": "ASA",
      "airlineCode": "ASA",
      "origin": null,
      "originCode": null,
      "destination": "Portland Intl",
      "destinationCode": "PDX",
      "scheduled": "2026-03-22T22:23:00Z",
      "estimated": "2026-03-23T00:07:00Z",
      "status": "Scheduled",
      "terminal": null,
      "gate": null
    },
    {
      "flightNumber": "WN109",
      "airline": "SWA",
      "airlineCode": "SWA",
      "origin": null,
      "originCode": null,
      "destination": "William P Hobby",
      "destinationCode": "HOU",
      "scheduled": "2026-03-22T22:25:00Z",
      "estimated": "2026-03-22T22:28:00Z",
      "status": "Scheduled",
      "terminal": null,
      "gate": null
    },
    {
      "flightNumber": "WS2151",
      "airline": "WJA",
      "airlineCode": "WJA",
      "origin": null,
      "originCode": null,
      "destination": "Vancouver Int'l",
      "destinationCode": "YVR",
      "scheduled": "2026-03-22T22:35:00Z",
      "estimated": "2026-03-22T22:35:00Z",
      "status": "Scheduled",
      "terminal": null,
      "gate": null
    },
    {
      "flightNumber": "5D881",
      "airline": "SLI",
      "airlineCode": "SLI",
      "origin": null,
      "originCode": null,
      "destination": "Mexico City Santa Lucía Airport",
      "destinationCode": "NLU",
      "scheduled": "2026-03-22T22:38:00Z",
      "estimated": "2026-03-22T22:38:00Z",
      "status": "Scheduled",
      "terminal": null,
      "gate": null
    },
    {
      "flightNumber": "WS2241",
      "airline": "WJA",
      "airlineCode": "WJA",
      "origin": null,
      "originCode": null,
      "destination": "Calgary Int'l",
      "destinationCode": "YYC",
      "scheduled": "2026-03-22T22:40:00Z",
      "estimated": "2026-03-22T22:40:00Z",
      "status": "Scheduled",
      "terminal": null,
      "gate": null
    },
    {
      "flightNumber": "Y43123",
      "airline": "VOI",
      "airlineCode": "VOI",
      "origin": null,
      "originCode": null,
      "destination": "General Abelardo L. Rodriguez Int'l",
      "destinationCode": "TIJ",
      "scheduled": "2026-03-22T22:46:00Z",
      "estimated": "2026-03-22T22:46:00Z",
      "status": "Scheduled",
      "terminal": null,
      "gate": null
    },
    {
      "flightNumber": "AC971",
      "airline": "ACA",
      "airlineCode": "ACA",
      "origin": null,
      "originCode": null,
      "destination": "Vancouver Int'l",
      "destinationCode": "YVR",
      "scheduled": "2026-03-22T22:50:00Z",
      "estimated": "2026-03-22T22:54:00Z",
      "status": "Scheduled",
      "terminal": null,
      "gate": null
    },
    {
      "flightNumber": "TS107",
      "airline": "TSC",
      "airlineCode": "TSC",
      "origin": null,
      "originCode": null,
      "destination": "Montreal-Trudeau",
      "destinationCode": "YUL",
      "scheduled": "2026-03-22T23:00:00Z",
      "estimated": "2026-03-22T23:00:00Z",
      "status": "Scheduled",
      "terminal": null,
      "gate": null
    },
    {
      "flightNumber": "N68VP",
      "airline": "—",
      "airlineCode": "",
      "origin": null,
      "originCode": null,
      "destination": "Laredo Intl",
      "destinationCode": "LRD",
      "scheduled": "2026-03-22T23:00:00Z",
      "estimated": "2026-03-22T23:10:00Z",
      "status": "Scheduled",
      "terminal": null,
      "gate": null
    },
    {
      "flightNumber": "DL1922",
      "airline": "DAL",
      "airlineCode": "DAL",
      "origin": null,
      "originCode": null,
      "destination": "Seattle-Tacoma Intl",
      "destinationCode": "SEA",
      "scheduled": "2026-03-22T23:08:00Z",
      "estimated": "2026-03-22T23:13:00Z",
      "status": "Scheduled",
      "terminal": null,
      "gate": null
    },
    {
      "flightNumber": "PD794",
      "airline": "POE",
      "airlineCode": "POE",
      "origin": null,
      "originCode": null,
      "destination": "Ottawa Macdonald-Cartier Int'l",
      "destinationCode": "YOW",
      "scheduled": "2026-03-22T23:10:00Z",
      "estimated": "2026-03-22T23:00:00Z",
      "status": "Scheduled",
      "terminal": null,
      "gate": null
    },
    {
      "flightNumber": "LXJ365",
      "airline": "LXJ",
      "airlineCode": "LXJ",
      "origin": null,
      "originCode": null,
      "destination": "William P Hobby",
      "destinationCode": "HOU",
      "scheduled": "2026-03-22T23:13:48Z",
      "estimated": "2026-03-22T23:13:48Z",
      "status": "Scheduled",
      "terminal": null,
      "gate": null
    },
    {
      "flightNumber": "Y41313",
      "airline": "VOI",
      "airlineCode": "VOI",
      "origin": null,
      "originCode": null,
      "destination": "Don Miguel Hidalgo y Costilla Int'l",
      "destinationCode": "GDL",
      "scheduled": "2026-03-22T23:19:30Z",
      "estimated": "2026-03-22T23:20:00Z",
      "status": "Scheduled",
      "terminal": null,
      "gate": null
    },
    {
      "flightNumber": "WS2215",
      "airline": "WJA",
      "airlineCode": "WJA",
      "origin": null,
      "originCode": null,
      "destination": "Kelowna Int'l",
      "destinationCode": "YLW",
      "scheduled": "2026-03-22T23:40:00Z",
      "estimated": "2026-03-22T23:40:00Z",
      "status": "Scheduled",
      "terminal": null,
      "gate": null
    },
    {
      "flightNumber": "AA3106",
      "airline": "AAL",
      "airlineCode": "AAL",
      "origin": null,
      "originCode": null,
      "destination": "Phoenix Sky Harbor Intl",
      "destinationCode": "PHX",
      "scheduled": "2026-03-22T23:46:00Z",
      "estimated": "2026-03-23T00:52:00Z",
      "status": "Scheduled",
      "terminal": null,
      "gate": null
    },
    {
      "flightNumber": "AS690",
      "airline": "ASA",
      "airlineCode": "ASA",
      "origin": null,
      "originCode": null,
      "destination": "San Francisco Int'l",
      "destinationCode": "SFO",
      "scheduled": "2026-03-22T23:50:00Z",
      "estimated": "2026-03-22T23:50:00Z",
      "status": "Scheduled",
      "terminal": null,
      "gate": null
    },
    {
      "flightNumber": "VB1169",
      "airline": "VIV",
      "airlineCode": "VIV",
      "origin": null,
      "originCode": null,
      "destination": "Lic. Benito Juarez Int'l",
      "destinationCode": "MEX",
      "scheduled": "2026-03-22T23:55:00Z",
      "estimated": "2026-03-22T23:55:00Z",
      "status": "Scheduled",
      "terminal": null,
      "gate": null
    },
    {
      "flightNumber": "Y45615",
      "airline": "VOI",
      "airlineCode": "VOI",
      "origin": null,
      "originCode": null,
      "destination": "General Mariano Escobedo Int'l",
      "destinationCode": "MTY",
      "scheduled": "2026-03-22T23:55:00Z",
      "estimated": "2026-03-22T23:55:00Z",
      "status": "Scheduled",
      "terminal": null,
      "gate": null
    },
    {
      "flightNumber": "Y47435",
      "airline": "VOI",
      "airlineCode": "VOI",
      "origin": null,
      "originCode": null,
      "destination": "General Rodolfo Sanchez Taboada Int'l",
      "destinationCode": "MXL",
      "scheduled": "2026-03-22T23:59:00Z",
      "estimated": "2026-03-22T23:59:00Z",
      "status": "Scheduled",
      "terminal": null,
      "gate": null
    },
    {
      "flightNumber": "VB4345",
      "airline": "VIV",
      "airlineCode": "VIV",
      "origin": null,
      "originCode": null,
      "destination": "General Mariano Escobedo Int'l",
      "destinationCode": "MTY",
      "scheduled": "2026-03-23T00:25:00Z",
      "estimated": "2026-03-23T00:25:00Z",
      "status": "Scheduled",
      "terminal": null,
      "gate": null
    },
    {
      "flightNumber": "WS2603",
      "airline": "WJA",
      "airlineCode": "WJA",
      "origin": null,
      "originCode": null,
      "destination": "Edmonton Int'l",
      "destinationCode": "YEG",
      "scheduled": "2026-03-23T01:00:00Z",
      "estimated": "2026-03-23T01:00:00Z",
      "status": "Scheduled",
      "terminal": null,
      "gate": null
    },
    {
      "flightNumber": "VB7123",
      "airline": "VIV",
      "airlineCode": "VIV",
      "origin": null,
      "originCode": null,
      "destination": "Don Miguel Hidalgo y Costilla Int'l",
      "destinationCode": "GDL",
      "scheduled": "2026-03-23T01:20:00Z",
      "estimated": "2026-03-23T01:20:00Z",
      "status": "Scheduled",
      "terminal": null,
      "gate": null
    },
    {
      "flightNumber": "N878EM",
      "airline": "—",
      "airlineCode": "",
      "origin": null,
      "originCode": null,
      "destination": "Brown Fld Muni",
      "destinationCode": "SDM",
      "scheduled": "2026-03-23T01:31:40Z",
      "estimated": "2026-03-23T01:31:40Z",
      "status": "Scheduled",
      "terminal": null,
      "gate": null
    },
    {
      "flightNumber": "AS1431",
      "airline": "ASA",
      "airlineCode": "ASA",
      "origin": null,
      "originCode": null,
      "destination": "Los Angeles Intl",
      "destinationCode": "LAX",
      "scheduled": "2026-03-23T01:36:00Z",
      "estimated": "2026-03-23T01:36:00Z",
      "status": "Scheduled",
      "terminal": null,
      "gate": null
    },
    {
      "flightNumber": "XN1445",
      "airline": "MXA",
      "airlineCode": "MXA",
      "origin": null,
      "originCode": null,
      "destination": "Mexico City Santa Lucía Airport",
      "destinationCode": "NLU",
      "scheduled": "2026-03-23T01:55:00Z",
      "estimated": "2026-03-23T01:55:00Z",
      "status": "Scheduled",
      "terminal": null,
      "gate": null
    },
    {
      "flightNumber": "VB4349",
      "airline": "VIV",
      "airlineCode": "VIV",
      "origin": null,
      "originCode": null,
      "destination": "General Mariano Escobedo Int'l",
      "destinationCode": "MTY",
      "scheduled": "2026-03-23T04:15:00Z",
      "estimated": "2026-03-23T04:15:00Z",
      "status": "Scheduled",
      "terminal": null,
      "gate": null
    },
    {
      "flightNumber": "WS2611",
      "airline": "WJA",
      "airlineCode": "WJA",
      "origin": null,
      "originCode": null,
      "destination": "Winnipeg Int'l",
      "destinationCode": "YWG",
      "scheduled": "2026-03-23T04:40:00Z",
      "estimated": "2026-03-23T04:40:00Z",
      "status": "Scheduled",
      "terminal": null,
      "gate": null
    }
  ]
}