{
  "lastUpdated": "2026-03-05T19:49:09.907Z",
  "airport": {
    "code": "PVR",
    "icao": "MMPR",
    "name": "Gustavo Díaz Ordaz International Airport",
    "city": "Puerto Vallarta",
    "timezone": "America/Mexico_City"
  },
  "arrivals": [
    {
      "flightNumber": "HU7926",
      "airline": "CHH",
      "airlineCode": "CHH",
      "origin": "Lic. Benito Juarez Int'l",
      "originCode": "MEX",
      "destination": null,
      "destinationCode": null,
      "scheduled": "2026-03-05T11:47:00Z",
      "estimated": "2026-03-05T12:09:17Z",
      "actual": "2026-03-05T12:09:17Z",
      "status": "Landed",
      "terminal": null,
      "gate": null
    },
    {
      "flightNumber": "VB1166",
      "airline": "VIV",
      "airlineCode": "VIV",
      "origin": "Lic. Benito Juarez Int'l",
      "originCode": "MEX",
      "destination": null,
      "destinationCode": null,
      "scheduled": "2026-03-05T13:12:00Z",
      "estimated": "2026-03-05T13:16:18Z",
      "actual": "2026-03-05T13:16:18Z",
      "status": "Landed",
      "terminal": null,
      "gate": null
    },
    {
      "flightNumber": "ANX1204",
      "airline": "ANX",
      "airlineCode": "ANX",
      "origin": "Lic. Benito Juarez Int'l",
      "originCode": "MEX",
      "destination": null,
      "destinationCode": null,
      "scheduled": "2026-03-05T14:09:22Z",
      "estimated": "2026-03-05T14:09:22Z",
      "actual": "2026-03-05T14:09:22Z",
      "status": "Landed",
      "terminal": null,
      "gate": null
    },
    {
      "flightNumber": "AM332",
      "airline": "AMX",
      "airlineCode": "AMX",
      "origin": "Lic. Benito Juarez Int'l",
      "originCode": "MEX",
      "destination": null,
      "destinationCode": null,
      "scheduled": "2026-03-05T14:50:00Z",
      "estimated": "2026-03-05T14:53:10Z",
      "actual": "2026-03-05T14:53:10Z",
      "status": "Landed",
      "terminal": null,
      "gate": null
    },
    {
      "flightNumber": "FIC220",
      "airline": "—",
      "airlineCode": "",
      "origin": "Don Miguel Hidalgo y Costilla Int'l",
      "originCode": "GDL",
      "destination": null,
      "destinationCode": null,
      "scheduled": "2026-03-05T15:25:36Z",
      "estimated": "2026-03-05T15:20:14Z",
      "actual": "2026-03-05T15:20:14Z",
      "status": "Landed",
      "terminal": null,
      "gate": null
    },
    {
      "flightNumber": "VB7350",
      "airline": "VIV",
      "airlineCode": "VIV",
      "origin": "Mexico City Santa Lucía Airport",
      "originCode": "NLU",
      "destination": null,
      "destinationCode": null,
      "scheduled": "2026-03-05T15:53:00Z",
      "estimated": "2026-03-05T15:53:18Z",
      "actual": "2026-03-05T15:53:18Z",
      "status": "Landed",
      "terminal": null,
      "gate": null
    },
    {
      "flightNumber": "XB-CIZ",
      "airline": "—",
      "airlineCode": "",
      "origin": "Lic. Gustavo Diaz Ordaz Int'l",
      "originCode": "PVR",
      "destination": null,
      "destinationCode": null,
      "scheduled": "2026-03-05T16:41:17Z",
      "estimated": "2026-03-05T16:41:17Z",
      "actual": "2026-03-05T16:41:17Z",
      "status": "Landed",
      "terminal": null,
      "gate": null
    },
    {
      "flightNumber": "XB-EGU",
      "airline": "—",
      "airlineCode": "",
      "origin": "Del Norte Int'l",
      "originCode": "NTR",
      "destination": null,
      "destinationCode": null,
      "scheduled": "2026-03-05T16:43:40Z",
      "estimated": "2026-03-05T16:39:52Z",
      "actual": "2026-03-05T16:39:52Z",
      "status": "Landed",
      "terminal": null,
      "gate": null
    },
    {
      "flightNumber": "XA-PLJ",
      "airline": "—",
      "airlineCode": "",
      "origin": "Lic. Adolfo Lopez Mateos Int'l",
      "originCode": "TLC",
      "destination": null,
      "destinationCode": null,
      "scheduled": "2026-03-05T17:15:16Z",
      "estimated": "2026-03-05T17:15:16Z",
      "actual": "2026-03-05T17:15:16Z",
      "status": "Landed",
      "terminal": null,
      "gate": null
    },
    {
      "flightNumber": "DL1935",
      "airline": "DAL",
      "airlineCode": "DAL",
      "origin": "Minneapolis/St Paul Intl",
      "originCode": "MSP",
      "destination": null,
      "destinationCode": null,
      "scheduled": "2026-03-05T17:22:00Z",
      "estimated": "2026-03-05T17:13:14Z",
      "actual": "2026-03-05T17:13:14Z",
      "status": "Landed",
      "terminal": null,
      "gate": null
    },
    {
      "flightNumber": "AS1430",
      "airline": "ASA",
      "airlineCode": "ASA",
      "origin": "Los Angeles Intl",
      "originCode": "LAX",
      "destination": null,
      "destinationCode": null,
      "scheduled": "2026-03-05T17:41:00Z",
      "estimated": "2026-03-05T17:37:52Z",
      "actual": "2026-03-05T17:37:52Z",
      "status": "Landed",
      "terminal": null,
      "gate": null
    },
    {
      "flightNumber": "F82622",
      "airline": "FLE",
      "airlineCode": "FLE",
      "origin": "Toronto Pearson Int'l",
      "originCode": "YYZ",
      "destination": null,
      "destinationCode": null,
      "scheduled": "2026-03-05T17:52:00Z",
      "estimated": "2026-03-05T18:05:02Z",
      "actual": "2026-03-05T18:05:02Z",
      "status": "Landed",
      "terminal": null,
      "gate": null
    },
    {
      "flightNumber": "AM330",
      "airline": "AMX",
      "airlineCode": "AMX",
      "origin": "Lic. Benito Juarez Int'l",
      "originCode": "MEX",
      "destination": null,
      "destinationCode": null,
      "scheduled": "2026-03-05T17:52:00Z",
      "estimated": "2026-03-05T18:02:22Z",
      "actual": "2026-03-05T18:02:22Z",
      "status": "Landed",
      "terminal": null,
      "gate": null
    },
    {
      "flightNumber": "WN633",
      "airline": "SWA",
      "airlineCode": "SWA",
      "origin": "Austin-Bergstrom Intl",
      "originCode": "AUS",
      "destination": null,
      "destinationCode": null,
      "scheduled": "2026-03-05T17:54:00Z",
      "estimated": "2026-03-05T17:49:25Z",
      "actual": "2026-03-05T17:49:25Z",
      "status": "Landed",
      "terminal": null,
      "gate": null
    },
    {
      "flightNumber": "VB9144",
      "airline": "VIV",
      "airlineCode": "VIV",
      "origin": "Lic. Adolfo Lopez Mateos Int'l",
      "originCode": "TLC",
      "destination": null,
      "destinationCode": null,
      "scheduled": "2026-03-05T17:55:00Z",
      "estimated": "2026-03-05T17:46:36Z",
      "actual": "2026-03-05T17:46:36Z",
      "status": "Landed",
      "terminal": null,
      "gate": null
    },
    {
      "flightNumber": "WS2112",
      "airline": "WJA",
      "airlineCode": "WJA",
      "origin": "Edmonton Int'l",
      "originCode": "YEG",
      "destination": null,
      "destinationCode": null,
      "scheduled": "2026-03-05T18:05:00Z",
      "estimated": "2026-03-05T18:09:46Z",
      "actual": "2026-03-05T18:09:46Z",
      "status": "Landed",
      "terminal": null,
      "gate": null
    },
    {
      "flightNumber": "PD793",
      "airline": "POE",
      "airlineCode": "POE",
      "origin": "Ottawa Macdonald-Cartier Int'l",
      "originCode": "YOW",
      "destination": null,
      "destinationCode": null,
      "scheduled": "2026-03-05T18:05:00Z",
      "estimated": "2026-03-05T17:35:06Z",
      "actual": "2026-03-05T17:35:06Z",
      "status": "Landed",
      "terminal": null,
      "gate": null
    },
    {
      "flightNumber": "WN1298",
      "airline": "SWA",
      "airlineCode": "SWA",
      "origin": "Phoenix Sky Harbor Intl",
      "originCode": "PHX",
      "destination": null,
      "destinationCode": null,
      "scheduled": "2026-03-05T18:13:00Z",
      "estimated": "2026-03-05T18:15:32Z",
      "actual": "2026-03-05T18:15:32Z",
      "status": "Landed",
      "terminal": null,
      "gate": null
    },
    {
      "flightNumber": "Y4280",
      "airline": "VOI",
      "airlineCode": "VOI",
      "origin": "Lic. Benito Juarez Int'l",
      "originCode": "MEX",
      "destination": null,
      "destinationCode": null,
      "scheduled": "2026-03-05T18:22:00Z",
      "estimated": "2026-03-05T18:28:29Z",
      "actual": "2026-03-05T18:28:29Z",
      "status": "Landed",
      "terminal": null,
      "gate": null
    },
    {
      "flightNumber": "DL1901",
      "airline": "DAL",
      "airlineCode": "DAL",
      "origin": "Detroit Metro Wayne Co",
      "originCode": "DTW",
      "destination": null,
      "destinationCode": null,
      "scheduled": "2026-03-05T18:25:00Z",
      "estimated": "2026-03-05T18:07:18Z",
      "actual": "2026-03-05T18:07:18Z",
      "status": "Landed",
      "terminal": null,
      "gate": null
    },
    {
      "flightNumber": "N850ZS",
      "airline": "—",
      "airlineCode": "",
      "origin": "Sugar Land Rgnl",
      "originCode": "KSGR",
      "destination": null,
      "destinationCode": null,
      "scheduled": "2026-03-05T18:29:00Z",
      "estimated": "2026-03-05T18:39:00Z",
      "actual": "2026-03-05T18:39:00Z",
      "status": "Landed",
      "terminal": null,
      "gate": null
    },
    {
      "flightNumber": "AA3319",
      "airline": "AAL",
      "airlineCode": "AAL",
      "origin": "Chicago O'Hare Intl",
      "originCode": "ORD",
      "destination": null,
      "destinationCode": null,
      "scheduled": "2026-03-05T18:31:00Z",
      "estimated": "2026-03-05T18:47:28Z",
      "actual": "2026-03-05T18:47:28Z",
      "status": "Landed",
      "terminal": null,
      "gate": null
    },
    {
      "flightNumber": "AS1486",
      "airline": "ASA",
      "airlineCode": "ASA",
      "origin": "San Jose Int'l",
      "originCode": "SJC",
      "destination": null,
      "destinationCode": null,
      "scheduled": "2026-03-05T18:31:00Z",
      "estimated": "2026-03-05T17:55:51Z",
      "actual": "2026-03-05T17:55:51Z",
      "status": "Landed",
      "terminal": null,
      "gate": null
    },
    {
      "flightNumber": "N402FB",
      "airline": "—",
      "airlineCode": "",
      "origin": "Del Norte Int'l",
      "originCode": "NTR",
      "destination": null,
      "destinationCode": null,
      "scheduled": "2026-03-05T18:32:44Z",
      "estimated": "2026-03-05T18:31:10Z",
      "actual": "2026-03-05T18:31:10Z",
      "status": "Landed",
      "terminal": null,
      "gate": null
    },
    {
      "flightNumber": "WS2250",
      "airline": "WJA",
      "airlineCode": "WJA",
      "origin": "Calgary Int'l",
      "originCode": "YYC",
      "destination": null,
      "destinationCode": null,
      "scheduled": "2026-03-05T18:36:00Z",
      "estimated": "2026-03-05T18:33:07Z",
      "actual": "2026-03-05T18:33:07Z",
      "status": "Landed",
      "terminal": null,
      "gate": null
    },
    {
      "flightNumber": "DL1941",
      "airline": "DAL",
      "airlineCode": "DAL",
      "origin": "Hartsfield-Jackson Intl",
      "originCode": "ATL",
      "destination": null,
      "destinationCode": null,
      "scheduled": "2026-03-05T18:40:00Z",
      "estimated": "2026-03-05T18:35:25Z",
      "actual": "2026-03-05T18:35:25Z",
      "status": "Landed",
      "terminal": null,
      "gate": null
    },
    {
      "flightNumber": "N900MY",
      "airline": "—",
      "airlineCode": "",
      "origin": "McClellan-Palomar",
      "originCode": "CLD",
      "destination": null,
      "destinationCode": null,
      "scheduled": "2026-03-05T18:42:00Z",
      "estimated": "2026-03-05T19:01:45Z",
      "actual": "2026-03-05T19:01:45Z",
      "status": "Landed",
      "terminal": null,
      "gate": null
    },
    {
      "flightNumber": "Y45612",
      "airline": "VOI",
      "airlineCode": "VOI",
      "origin": "General Mariano Escobedo Int'l",
      "originCode": "MTY",
      "destination": null,
      "destinationCode": null,
      "scheduled": "2026-03-05T18:47:00Z",
      "estimated": "2026-03-05T19:50:00Z",
      "status": "En Route",
      "terminal": null,
      "gate": null
    },
    {
      "flightNumber": "UA1622",
      "airline": "UAL",
      "airlineCode": "UAL",
      "origin": "Houston Bush Int'ctl",
      "originCode": "IAH",
      "destination": null,
      "destinationCode": null,
      "scheduled": "2026-03-05T18:49:00Z",
      "estimated": "2026-03-05T18:41:52Z",
      "actual": "2026-03-05T18:41:52Z",
      "status": "Landed",
      "terminal": null,
      "gate": null
    },
    {
      "flightNumber": "WS2150",
      "airline": "WJA",
      "airlineCode": "WJA",
      "origin": "Vancouver Int'l",
      "originCode": "YVR",
      "destination": null,
      "destinationCode": null,
      "scheduled": "2026-03-05T18:51:00Z",
      "estimated": "2026-03-05T18:50:29Z",
      "actual": "2026-03-05T18:50:29Z",
      "status": "Landed",
      "terminal": null,
      "gate": null
    },
    {
      "flightNumber": "N809GG",
      "airline": "—",
      "airlineCode": "",
      "origin": "Lic. Adolfo Lopez Mateos Int'l",
      "originCode": "TLC",
      "destination": null,
      "destinationCode": null,
      "scheduled": "2026-03-05T18:54:31Z",
      "estimated": "2026-03-05T18:56:12Z",
      "actual": "2026-03-05T18:56:12Z",
      "status": "Landed",
      "terminal": null,
      "gate": null
    },
    {
      "flightNumber": "AC1349",
      "airline": "ACA",
      "airlineCode": "ACA",
      "origin": "Toronto Pearson Int'l",
      "originCode": "YYZ",
      "destination": null,
      "destinationCode": null,
      "scheduled": "2026-03-05T19:03:00Z",
      "estimated": "2026-03-05T19:12:28Z",
      "actual": "2026-03-05T19:12:28Z",
      "status": "Landed",
      "terminal": null,
      "gate": null
    },
    {
      "flightNumber": "Y43120",
      "airline": "VOI",
      "airlineCode": "VOI",
      "origin": "General Abelardo L. Rodriguez Int'l",
      "originCode": "TIJ",
      "destination": null,
      "destinationCode": null,
      "scheduled": "2026-03-05T19:08:00Z",
      "estimated": "2026-03-05T19:04:51Z",
      "actual": "2026-03-05T19:04:51Z",
      "status": "Landed",
      "terminal": null,
      "gate": null
    },
    {
      "flightNumber": "WS2452",
      "airline": "WJA",
      "airlineCode": "WJA",
      "origin": "Winnipeg Int'l",
      "originCode": "YWG",
      "destination": null,
      "destinationCode": null,
      "scheduled": "2026-03-05T19:09:00Z",
      "estimated": "2026-03-05T19:15:23Z",
      "actual": "2026-03-05T19:15:23Z",
      "status": "Landed",
      "terminal": null,
      "gate": null
    },
    {
      "flightNumber": "AA3044",
      "airline": "AAL",
      "airlineCode": "AAL",
      "origin": "Phoenix Sky Harbor Intl",
      "originCode": "PHX",
      "destination": null,
      "destinationCode": null,
      "scheduled": "2026-03-05T19:11:00Z",
      "estimated": "2026-03-05T18:44:28Z",
      "actual": "2026-03-05T18:44:28Z",
      "status": "Landed",
      "terminal": null,
      "gate": null
    },
    {
      "flightNumber": "UA1452",
      "airline": "UAL",
      "airlineCode": "UAL",
      "origin": "Chicago O'Hare Intl",
      "originCode": "ORD",
      "destination": null,
      "destinationCode": null,
      "scheduled": "2026-03-05T19:13:00Z",
      "estimated": "2026-03-05T20:23:00Z",
      "status": "En Route",
      "terminal": null,
      "gate": null
    },
    {
      "flightNumber": "WN514",
      "airline": "SWA",
      "airlineCode": "SWA",
      "origin": "Denver Intl",
      "originCode": "DEN",
      "destination": null,
      "destinationCode": null,
      "scheduled": "2026-03-05T19:14:00Z",
      "estimated": "2026-03-05T19:08:27Z",
      "actual": "2026-03-05T19:08:27Z",
      "status": "Landed",
      "terminal": null,
      "gate": null
    },
    {
      "flightNumber": "1I668",
      "airline": "EJA",
      "airlineCode": "EJA",
      "origin": "Salt Lake City Intl",
      "originCode": "SLC",
      "destination": null,
      "destinationCode": null,
      "scheduled": "2026-03-05T19:14:00Z",
      "estimated": "2026-03-05T19:54:06Z",
      "status": "En Route",
      "terminal": null,
      "gate": null
    },
    {
      "flightNumber": "AS1446",
      "airline": "ASA",
      "airlineCode": "ASA",
      "origin": "Portland Intl",
      "originCode": "PDX",
      "destination": null,
      "destinationCode": null,
      "scheduled": "2026-03-05T19:18:00Z",
      "estimated": "2026-03-05T19:27:21Z",
      "actual": "2026-03-05T19:27:21Z",
      "status": "Landed",
      "terminal": null,
      "gate": null
    },
    {
      "flightNumber": "LET6245",
      "airline": "LET",
      "airlineCode": "LET",
      "origin": "Del Norte Int'l",
      "originCode": "NTR",
      "destination": null,
      "destinationCode": null,
      "scheduled": "2026-03-05T19:21:30Z",
      "estimated": "2026-03-05T19:22:09Z",
      "actual": "2026-03-05T19:22:09Z",
      "status": "Landed",
      "terminal": null,
      "gate": null
    },
    {
      "flightNumber": "WS2380",
      "airline": "WJA",
      "airlineCode": "WJA",
      "origin": "Regina Int'l",
      "originCode": "YQR",
      "destination": null,
      "destinationCode": null,
      "scheduled": "2026-03-05T19:25:00Z",
      "estimated": "2026-03-05T19:42:42Z",
      "actual": "2026-03-05T19:42:42Z",
      "status": "Landed",
      "terminal": null,
      "gate": null
    },
    {
      "flightNumber": "AA1215",
      "airline": "AAL",
      "airlineCode": "AAL",
      "origin": "Dallas-Fort Worth Intl",
      "originCode": "DFW",
      "destination": null,
      "destinationCode": null,
      "scheduled": "2026-03-05T19:26:00Z",
      "estimated": "2026-03-05T19:19:48Z",
      "actual": "2026-03-05T19:19:48Z",
      "status": "Landed",
      "terminal": null,
      "gate": null
    },
    {
      "flightNumber": "DL1862",
      "airline": "DAL",
      "airlineCode": "DAL",
      "origin": "Minneapolis/St Paul Intl",
      "originCode": "MSP",
      "destination": null,
      "destinationCode": null,
      "scheduled": "2026-03-05T19:30:00Z",
      "estimated": "2026-03-05T19:24:38Z",
      "actual": "2026-03-05T19:24:38Z",
      "status": "Landed",
      "terminal": null,
      "gate": null
    },
    {
      "flightNumber": "Y41312",
      "airline": "VOI",
      "airlineCode": "VOI",
      "origin": "Don Miguel Hidalgo y Costilla Int'l",
      "originCode": "GDL",
      "destination": null,
      "destinationCode": null,
      "scheduled": "2026-03-05T19:43:20Z",
      "estimated": "2026-03-05T19:31:02Z",
      "actual": "2026-03-05T19:31:02Z",
      "status": "Landed",
      "terminal": null,
      "gate": null
    },
    {
      "flightNumber": "VB4340",
      "airline": "VIV",
      "airlineCode": "VIV",
      "origin": "General Mariano Escobedo Int'l",
      "originCode": "MTY",
      "destination": null,
      "destinationCode": null,
      "scheduled": "2026-03-05T19:50:00Z",
      "estimated": "2026-03-05T19:45:56Z",
      "actual": "2026-03-05T19:45:56Z",
      "status": "Landed",
      "terminal": null,
      "gate": null
    },
    {
      "flightNumber": "Y4560",
      "airline": "VOI",
      "airlineCode": "VOI",
      "origin": "Lic. Adolfo Lopez Mateos Int'l",
      "originCode": "TLC",
      "destination": null,
      "destinationCode": null,
      "scheduled": "2026-03-05T19:50:00Z",
      "estimated": "2026-03-05T19:49:02Z",
      "status": "En Route",
      "terminal": null,
      "gate": null
    },
    {
      "flightNumber": "AA1188",
      "airline": "AAL",
      "airlineCode": "AAL",
      "origin": "Los Angeles Intl",
      "originCode": "LAX",
      "destination": null,
      "destinationCode": null,
      "scheduled": "2026-03-05T19:57:00Z",
      "estimated": "2026-03-05T19:40:13Z",
      "actual": "2026-03-05T19:40:13Z",
      "status": "Landed",
      "terminal": null,
      "gate": null
    },
    {
      "flightNumber": "AS248",
      "airline": "ASA",
      "airlineCode": "ASA",
      "origin": "John F Kennedy Intl",
      "originCode": "JFK",
      "destination": null,
      "destinationCode": null,
      "scheduled": "2026-03-05T19:59:00Z",
      "estimated": "2026-03-05T20:07:00Z",
      "status": "En Route",
      "terminal": null,
      "gate": null
    },
    {
      "flightNumber": "UA2257",
      "airline": "UAL",
      "airlineCode": "UAL",
      "origin": "Denver Intl",
      "originCode": "DEN",
      "destination": null,
      "destinationCode": null,
      "scheduled": "2026-03-05T20:05:00Z",
      "estimated": "2026-03-05T19:37:14Z",
      "actual": "2026-03-05T19:37:14Z",
      "status": "Landed",
      "terminal": null,
      "gate": null
    },
    {
      "flightNumber": "VB8032",
      "airline": "VIV",
      "airlineCode": "VIV",
      "origin": "Abraham Gonzalez Int'l",
      "originCode": "CJS",
      "destination": null,
      "destinationCode": null,
      "scheduled": "2026-03-05T20:10:00Z",
      "estimated": "2026-03-05T20:01:00Z",
      "status": "En Route",
      "terminal": null,
      "gate": null
    },
    {
      "flightNumber": "XA-ARO",
      "airline": "—",
      "airlineCode": "",
      "origin": "Del Norte Int'l",
      "originCode": "NTR",
      "destination": null,
      "destinationCode": null,
      "scheduled": "2026-03-05T20:14:00Z",
      "estimated": "2026-03-05T20:26:42Z",
      "status": "En Route",
      "terminal": null,
      "gate": null
    },
    {
      "flightNumber": "VB7412",
      "airline": "VIV",
      "airlineCode": "VIV",
      "origin": "Don Miguel Hidalgo y Costilla Int'l",
      "originCode": "GDL",
      "destination": null,
      "destinationCode": null,
      "scheduled": "2026-03-05T20:19:10Z",
      "estimated": "2026-03-05T20:20:16Z",
      "status": "Scheduled",
      "terminal": null,
      "gate": null
    },
    {
      "flightNumber": "AM334",
      "airline": "AMX",
      "airlineCode": "AMX",
      "origin": "Lic. Benito Juarez Int'l",
      "originCode": "MEX",
      "destination": null,
      "destinationCode": null,
      "scheduled": "2026-03-05T20:20:00Z",
      "estimated": "2026-03-05T20:35:00Z",
      "status": "En Route",
      "terminal": null,
      "gate": null
    },
    {
      "flightNumber": "WN763",
      "airline": "SWA",
      "airlineCode": "SWA",
      "origin": "John Wayne",
      "originCode": "SNA",
      "destination": null,
      "destinationCode": null,
      "scheduled": "2026-03-05T20:23:00Z",
      "estimated": "2026-03-05T20:30:00Z",
      "status": "En Route",
      "terminal": null,
      "gate": null
    },
    {
      "flightNumber": "UA1212",
      "airline": "UAL",
      "airlineCode": "UAL",
      "origin": "San Francisco Int'l",
      "originCode": "SFO",
      "destination": null,
      "destinationCode": null,
      "scheduled": "2026-03-05T20:24:00Z",
      "estimated": "2026-03-05T20:08:00Z",
      "status": "En Route",
      "terminal": null,
      "gate": null
    },
    {
      "flightNumber": "F82800",
      "airline": "FLE",
      "airlineCode": "FLE",
      "origin": "Vancouver Int'l",
      "originCode": "YVR",
      "destination": null,
      "destinationCode": null,
      "scheduled": "2026-03-05T20:25:00Z",
      "estimated": "2026-03-05T20:06:00Z",
      "status": "En Route",
      "terminal": null,
      "gate": null
    },
    {
      "flightNumber": "Y47304",
      "airline": "VOI",
      "airlineCode": "VOI",
      "origin": "Del Bajio Guanajuato Int'l",
      "originCode": "BJX",
      "destination": null,
      "destinationCode": null,
      "scheduled": "2026-03-05T20:28:00Z",
      "estimated": "2026-03-05T20:08:00Z",
      "status": "En Route",
      "terminal": null,
      "gate": null
    },
    {
      "flightNumber": "AC999",
      "airline": "ACA",
      "airlineCode": "ACA",
      "origin": "Montreal-Trudeau",
      "originCode": "YUL",
      "destination": null,
      "destinationCode": null,
      "scheduled": "2026-03-05T20:28:00Z",
      "estimated": "2026-03-05T20:17:56Z",
      "status": "En Route",
      "terminal": null,
      "gate": null
    },
    {
      "flightNumber": "AS659",
      "airline": "ASA",
      "airlineCode": "ASA",
      "origin": "Seattle-Tacoma Intl",
      "originCode": "SEA",
      "destination": null,
      "destinationCode": null,
      "scheduled": "2026-03-05T20:34:00Z",
      "estimated": "2026-03-05T20:31:00Z",
      "status": "En Route",
      "terminal": null,
      "gate": null
    },
    {
      "flightNumber": "UA304",
      "airline": "UAL",
      "airlineCode": "UAL",
      "origin": "Houston Bush Int'ctl",
      "originCode": "IAH",
      "destination": null,
      "destinationCode": null,
      "scheduled": "2026-03-05T20:34:00Z",
      "estimated": "2026-03-05T20:26:58Z",
      "status": "Scheduled",
      "terminal": null,
      "gate": null
    },
    {
      "flightNumber": "AA3272",
      "airline": "AAL",
      "airlineCode": "AAL",
      "origin": "Phoenix Sky Harbor Intl",
      "originCode": "PHX",
      "destination": null,
      "destinationCode": null,
      "scheduled": "2026-03-05T20:46:00Z",
      "estimated": "2026-03-05T20:15:00Z",
      "status": "En Route",
      "terminal": null,
      "gate": null
    },
    {
      "flightNumber": "WS2152",
      "airline": "WJA",
      "airlineCode": "WJA",
      "origin": "Vancouver Int'l",
      "originCode": "YVR",
      "destination": null,
      "destinationCode": null,
      "scheduled": "2026-03-05T20:51:00Z",
      "estimated": "2026-03-05T20:54:00Z",
      "status": "En Route",
      "terminal": null,
      "gate": null
    },
    {
      "flightNumber": "WS2040",
      "airline": "WJA",
      "airlineCode": "WJA",
      "origin": "Victoria Int'l",
      "originCode": "YYJ",
      "destination": null,
      "destinationCode": null,
      "scheduled": "2026-03-05T20:53:00Z",
      "estimated": "2026-03-05T20:30:58Z",
      "status": "En Route",
      "terminal": null,
      "gate": null
    },
    {
      "flightNumber": "Y47506",
      "airline": "VOI",
      "airlineCode": "VOI",
      "origin": "Queretaro Intercontinental Airport",
      "originCode": "QRO",
      "destination": null,
      "destinationCode": null,
      "scheduled": "2026-03-05T21:05:00Z",
      "estimated": "2026-03-05T21:05:12Z",
      "status": "Scheduled",
      "terminal": null,
      "gate": null
    },
    {
      "flightNumber": "WN108",
      "airline": "SWA",
      "airlineCode": "SWA",
      "origin": "William P Hobby",
      "originCode": "HOU",
      "destination": null,
      "destinationCode": null,
      "scheduled": "2026-03-05T21:12:00Z",
      "estimated": "2026-03-05T21:09:00Z",
      "status": "En Route",
      "terminal": null,
      "gate": null
    },
    {
      "flightNumber": "SY535",
      "airline": "SCX",
      "airlineCode": "SCX",
      "origin": "Minneapolis/St Paul Intl",
      "originCode": "MSP",
      "destination": null,
      "destinationCode": null,
      "scheduled": "2026-03-05T21:14:00Z",
      "estimated": "2026-03-05T20:59:00Z",
      "status": "En Route",
      "terminal": null,
      "gate": null
    },
    {
      "flightNumber": "DL1948",
      "airline": "DAL",
      "airlineCode": "DAL",
      "origin": "Salt Lake City Intl",
      "originCode": "SLC",
      "destination": null,
      "destinationCode": null,
      "scheduled": "2026-03-05T21:19:00Z",
      "estimated": "2026-03-05T20:58:00Z",
      "status": "En Route",
      "terminal": null,
      "gate": null
    },
    {
      "flightNumber": "VB5084",
      "airline": "VIV",
      "airlineCode": "VIV",
      "origin": "General Abelardo L. Rodriguez Int'l",
      "originCode": "TIJ",
      "destination": null,
      "destinationCode": null,
      "scheduled": "2026-03-05T21:20:00Z",
      "estimated": "2026-03-05T21:07:00Z",
      "status": "En Route",
      "terminal": null,
      "gate": null
    },
    {
      "flightNumber": "AA2019",
      "airline": "AAL",
      "airlineCode": "AAL",
      "origin": "Chicago O'Hare Intl",
      "originCode": "ORD",
      "destination": null,
      "destinationCode": null,
      "scheduled": "2026-03-05T21:23:00Z",
      "estimated": "2026-03-05T23:03:00Z",
      "status": "En Route",
      "terminal": null,
      "gate": null
    },
    {
      "flightNumber": "AA1288",
      "airline": "AAL",
      "airlineCode": "AAL",
      "origin": "Dallas-Fort Worth Intl",
      "originCode": "DFW",
      "destination": null,
      "destinationCode": null,
      "scheduled": "2026-03-05T21:27:00Z",
      "estimated": "2026-03-05T21:18:00Z",
      "status": "En Route",
      "terminal": null,
      "gate": null
    },
    {
      "flightNumber": "UA319",
      "airline": "UAL",
      "airlineCode": "UAL",
      "origin": "Los Angeles Intl",
      "originCode": "LAX",
      "destination": null,
      "destinationCode": null,
      "scheduled": "2026-03-05T21:29:00Z",
      "estimated": "2026-03-05T21:28:00Z",
      "status": "En Route",
      "terminal": null,
      "gate": null
    },
    {
      "flightNumber": "5D880",
      "airline": "SLI",
      "airlineCode": "SLI",
      "origin": "Mexico City Santa Lucía Airport",
      "originCode": "NLU",
      "destination": null,
      "destinationCode": null,
      "scheduled": "2026-03-05T21:35:00Z",
      "estimated": "2026-03-05T21:35:00Z",
      "status": "Scheduled",
      "terminal": null,
      "gate": null
    },
    {
      "flightNumber": "DL1793",
      "airline": "DAL",
      "airlineCode": "DAL",
      "origin": "Los Angeles Intl",
      "originCode": "LAX",
      "destination": null,
      "destinationCode": null,
      "scheduled": "2026-03-05T21:38:00Z",
      "estimated": "2026-03-05T21:24:00Z",
      "status": "En Route",
      "terminal": null,
      "gate": null
    },
    {
      "flightNumber": "Y43122",
      "airline": "VOI",
      "airlineCode": "VOI",
      "origin": "General Abelardo L. Rodriguez Int'l",
      "originCode": "TIJ",
      "destination": null,
      "destinationCode": null,
      "scheduled": "2026-03-05T21:42:00Z",
      "estimated": "2026-03-05T21:33:00Z",
      "status": "En Route",
      "terminal": null,
      "gate": null
    },
    {
      "flightNumber": "UA1708",
      "airline": "UAL",
      "airlineCode": "UAL",
      "origin": "Denver Intl",
      "originCode": "DEN",
      "destination": null,
      "destinationCode": null,
      "scheduled": "2026-03-05T21:48:00Z",
      "estimated": "2026-03-05T21:58:48Z",
      "status": "Scheduled",
      "terminal": null,
      "gate": null
    },
    {
      "flightNumber": "AS755",
      "airline": "ASA",
      "airlineCode": "ASA",
      "origin": "Seattle-Tacoma Intl",
      "originCode": "SEA",
      "destination": null,
      "destinationCode": null,
      "scheduled": "2026-03-05T22:00:00Z",
      "estimated": "2026-03-05T22:15:00Z",
      "status": "En Route",
      "terminal": null,
      "gate": null
    },
    {
      "flightNumber": "AS689",
      "airline": "ASA",
      "airlineCode": "ASA",
      "origin": "San Francisco Int'l",
      "originCode": "SFO",
      "destination": null,
      "destinationCode": null,
      "scheduled": "2026-03-05T22:03:00Z",
      "estimated": "2026-03-05T21:25:00Z",
      "status": "En Route",
      "terminal": null,
      "gate": null
    },
    {
      "flightNumber": "WS2450",
      "airline": "WJA",
      "airlineCode": "WJA",
      "origin": "Winnipeg Int'l",
      "originCode": "YWG",
      "destination": null,
      "destinationCode": null,
      "scheduled": "2026-03-05T22:04:00Z",
      "estimated": "2026-03-05T21:45:22Z",
      "status": "En Route",
      "terminal": null,
      "gate": null
    },
    {
      "flightNumber": "UA1585",
      "airline": "UAL",
      "airlineCode": "UAL",
      "origin": "San Francisco Int'l",
      "originCode": "SFO",
      "destination": null,
      "destinationCode": null,
      "scheduled": "2026-03-05T22:11:00Z",
      "estimated": "2026-03-05T22:11:41Z",
      "status": "Scheduled",
      "terminal": null,
      "gate": null
    },
    {
      "flightNumber": "AC970",
      "airline": "ACA",
      "airlineCode": "ACA",
      "origin": "Vancouver Int'l",
      "originCode": "YVR",
      "destination": null,
      "destinationCode": null,
      "scheduled": "2026-03-05T22:13:00Z",
      "estimated": "2026-03-05T22:29:18Z",
      "status": "En Route",
      "terminal": null,
      "gate": null
    },
    {
      "flightNumber": "Y41310",
      "airline": "VOI",
      "airlineCode": "VOI",
      "origin": "Don Miguel Hidalgo y Costilla Int'l",
      "originCode": "GDL",
      "destination": null,
      "destinationCode": null,
      "scheduled": "2026-03-05T22:14:20Z",
      "estimated": "2026-03-05T22:16:00Z",
      "status": "Scheduled",
      "terminal": null,
      "gate": null
    },
    {
      "flightNumber": "TS106",
      "airline": "TSC",
      "airlineCode": "TSC",
      "origin": "Montreal-Trudeau",
      "originCode": "YUL",
      "destination": null,
      "destinationCode": null,
      "scheduled": "2026-03-05T22:19:00Z",
      "estimated": "2026-03-05T22:03:00Z",
      "status": "En Route",
      "terminal": null,
      "gate": null
    },
    {
      "flightNumber": "WN772",
      "airline": "SWA",
      "airlineCode": "SWA",
      "origin": "San Diego Intl",
      "originCode": "SAN",
      "destination": null,
      "destinationCode": null,
      "scheduled": "2026-03-05T22:20:00Z",
      "estimated": "2026-03-05T22:20:00Z",
      "status": "Scheduled",
      "terminal": null,
      "gate": null
    },
    {
      "flightNumber": "DL1921",
      "airline": "DAL",
      "airlineCode": "DAL",
      "origin": "Seattle-Tacoma Intl",
      "originCode": "SEA",
      "destination": null,
      "destinationCode": null,
      "scheduled": "2026-03-05T22:21:00Z",
      "estimated": "2026-03-05T22:16:00Z",
      "status": "En Route",
      "terminal": null,
      "gate": null
    },
    {
      "flightNumber": "VB1168",
      "airline": "VIV",
      "airlineCode": "VIV",
      "origin": "Lic. Benito Juarez Int'l",
      "originCode": "MEX",
      "destination": null,
      "destinationCode": null,
      "scheduled": "2026-03-05T22:27:00Z",
      "estimated": "2026-03-05T22:27:14Z",
      "status": "Scheduled",
      "terminal": null,
      "gate": null
    },
    {
      "flightNumber": "WS2240",
      "airline": "WJA",
      "airlineCode": "WJA",
      "origin": "Calgary Int'l",
      "originCode": "YYC",
      "destination": null,
      "destinationCode": null,
      "scheduled": "2026-03-05T22:29:00Z",
      "estimated": "2026-03-05T22:06:13Z",
      "status": "En Route",
      "terminal": null,
      "gate": null
    },
    {
      "flightNumber": "AA3087",
      "airline": "AAL",
      "airlineCode": "AAL",
      "origin": "Phoenix Sky Harbor Intl",
      "originCode": "PHX",
      "destination": null,
      "destinationCode": null,
      "scheduled": "2026-03-05T22:30:00Z",
      "estimated": "2026-03-05T22:30:26Z",
      "status": "Scheduled",
      "terminal": null,
      "gate": null
    },
    {
      "flightNumber": "Y45614",
      "airline": "VOI",
      "airlineCode": "VOI",
      "origin": "General Mariano Escobedo Int'l",
      "originCode": "MTY",
      "destination": null,
      "destinationCode": null,
      "scheduled": "2026-03-05T22:56:00Z",
      "estimated": "2026-03-05T22:56:26Z",
      "status": "Scheduled",
      "terminal": null,
      "gate": null
    },
    {
      "flightNumber": "AS475",
      "airline": "ASA",
      "airlineCode": "ASA",
      "origin": "San Diego Intl",
      "originCode": "SAN",
      "destination": null,
      "destinationCode": null,
      "scheduled": "2026-03-05T23:15:00Z",
      "estimated": "2026-03-05T23:37:31Z",
      "status": "Scheduled",
      "terminal": null,
      "gate": null
    },
    {
      "flightNumber": "F82508",
      "airline": "FLE",
      "airlineCode": "FLE",
      "origin": "Calgary Int'l",
      "originCode": "YYC",
      "destination": null,
      "destinationCode": null,
      "scheduled": "2026-03-06T00:10:00Z",
      "estimated": "2026-03-06T00:01:00Z",
      "status": "En Route",
      "terminal": null,
      "gate": null
    },
    {
      "flightNumber": "PD769",
      "airline": "POE",
      "airlineCode": "POE",
      "origin": "Hamilton/John C. Munro Int'l",
      "originCode": "YHM",
      "destination": null,
      "destinationCode": null,
      "scheduled": "2026-03-06T00:11:00Z",
      "estimated": "2026-03-06T00:01:00Z",
      "status": "En Route",
      "terminal": null,
      "gate": null
    },
    {
      "flightNumber": "AM336",
      "airline": "AMX",
      "airlineCode": "AMX",
      "origin": "Lic. Benito Juarez Int'l",
      "originCode": "MEX",
      "destination": null,
      "destinationCode": null,
      "scheduled": "2026-03-06T00:12:00Z",
      "estimated": "2026-03-06T00:12:40Z",
      "status": "Scheduled",
      "terminal": null,
      "gate": null
    },
    {
      "flightNumber": "AS437",
      "airline": "ASA",
      "airlineCode": "ASA",
      "origin": "Los Angeles Intl",
      "originCode": "LAX",
      "destination": null,
      "destinationCode": null,
      "scheduled": "2026-03-06T00:22:00Z",
      "estimated": "2026-03-06T00:39:00Z",
      "status": "Scheduled",
      "terminal": null,
      "gate": null
    },
    {
      "flightNumber": "TS632",
      "airline": "TSC",
      "airlineCode": "TSC",
      "origin": "Quebec/Jean Lesage Int'l",
      "originCode": "YQB",
      "destination": null,
      "destinationCode": null,
      "scheduled": "2026-03-06T00:24:00Z",
      "estimated": "2026-03-06T00:24:02Z",
      "status": "En Route",
      "terminal": null,
      "gate": null
    },
    {
      "flightNumber": "VB7122",
      "airline": "VIV",
      "airlineCode": "VIV",
      "origin": "Don Miguel Hidalgo y Costilla Int'l",
      "originCode": "GDL",
      "destination": null,
      "destinationCode": null,
      "scheduled": "2026-03-06T01:00:00Z",
      "estimated": "2026-03-06T01:10:15Z",
      "status": "Scheduled",
      "terminal": null,
      "gate": null
    },
    {
      "flightNumber": "F82704",
      "airline": "FLE",
      "airlineCode": "FLE",
      "origin": "Edmonton Int'l",
      "originCode": "YEG",
      "destination": null,
      "destinationCode": null,
      "scheduled": "2026-03-06T01:03:00Z",
      "estimated": "2026-03-06T01:03:48Z",
      "status": "Scheduled",
      "terminal": null,
      "gate": null
    },
    {
      "flightNumber": "5D340",
      "airline": "SLI",
      "airlineCode": "SLI",
      "origin": "Lic. Benito Juarez Int'l",
      "originCode": "MEX",
      "destination": null,
      "destinationCode": null,
      "scheduled": "2026-03-06T04:34:00Z",
      "estimated": "2026-03-06T04:34:00Z",
      "status": "Scheduled",
      "terminal": null,
      "gate": null
    }
  ],
  "departures": [
    {
      "flightNumber": "AM331",
      "airline": "AMX",
      "airlineCode": "AMX",
      "origin": null,
      "originCode": null,
      "destination": "Lic. Benito Juarez Int'l",
      "destinationCode": "MEX",
      "scheduled": "2026-03-05T12:13:00Z",
      "estimated": "2026-03-05T12:19:08Z",
      "actual": "2026-03-05T12:19:08Z",
      "status": "Departed",
      "terminal": null,
      "gate": null
    },
    {
      "flightNumber": "HU7926",
      "airline": "CHH",
      "airlineCode": "CHH",
      "origin": null,
      "originCode": null,
      "destination": "Beijing Capital Int'l",
      "destinationCode": "PEK",
      "scheduled": "2026-03-05T14:00:00Z",
      "estimated": "2026-03-05T13:56:04Z",
      "actual": "2026-03-05T13:56:04Z",
      "status": "Departed",
      "terminal": null,
      "gate": null
    },
    {
      "flightNumber": "VB1167",
      "airline": "VIV",
      "airlineCode": "VIV",
      "origin": null,
      "originCode": null,
      "destination": "Lic. Benito Juarez Int'l",
      "destinationCode": "MEX",
      "scheduled": "2026-03-05T14:35:00Z",
      "estimated": "2026-03-05T14:24:11Z",
      "actual": "2026-03-05T14:24:11Z",
      "status": "Departed",
      "terminal": null,
      "gate": null
    },
    {
      "flightNumber": "XB-CIZ",
      "airline": "—",
      "airlineCode": "",
      "origin": null,
      "originCode": null,
      "destination": "Lic. Gustavo Diaz Ordaz Int'l",
      "destinationCode": "PVR",
      "scheduled": "2026-03-05T15:56:01Z",
      "estimated": "2026-03-05T15:56:01Z",
      "actual": "2026-03-05T15:56:01Z",
      "status": "Departed",
      "terminal": null,
      "gate": null
    },
    {
      "flightNumber": "AM335",
      "airline": "AMX",
      "airlineCode": "AMX",
      "origin": null,
      "originCode": null,
      "destination": "Lic. Benito Juarez Int'l",
      "destinationCode": "MEX",
      "scheduled": "2026-03-05T16:01:00Z",
      "estimated": "2026-03-05T16:06:36Z",
      "actual": "2026-03-05T16:06:36Z",
      "status": "Departed",
      "terminal": null,
      "gate": null
    },
    {
      "flightNumber": "VB7351",
      "airline": "VIV",
      "airlineCode": "VIV",
      "origin": null,
      "originCode": null,
      "destination": "Mexico City Santa Lucía Airport",
      "destinationCode": "NLU",
      "scheduled": "2026-03-05T17:05:00Z",
      "estimated": "2026-03-05T16:53:03Z",
      "actual": "2026-03-05T16:53:03Z",
      "status": "Departed",
      "terminal": null,
      "gate": null
    },
    {
      "flightNumber": "SY532",
      "airline": "SCX",
      "airlineCode": "SCX",
      "origin": null,
      "originCode": null,
      "destination": "Minneapolis/St Paul Intl",
      "destinationCode": "MSP",
      "scheduled": "2026-03-05T19:03:00Z",
      "estimated": "2026-03-05T19:03:00Z",
      "status": "Scheduled",
      "terminal": null,
      "gate": null
    },
    {
      "flightNumber": "PD794",
      "airline": "POE",
      "airlineCode": "POE",
      "origin": null,
      "originCode": null,
      "destination": "Ottawa Macdonald-Cartier Int'l",
      "destinationCode": "YOW",
      "scheduled": "2026-03-05T19:05:00Z",
      "estimated": "2026-03-05T19:13:52Z",
      "actual": "2026-03-05T19:13:52Z",
      "status": "Departed",
      "terminal": null,
      "gate": null
    },
    {
      "flightNumber": "WN632",
      "airline": "SWA",
      "airlineCode": "SWA",
      "origin": null,
      "originCode": null,
      "destination": "Austin-Bergstrom Intl",
      "destinationCode": "AUS",
      "scheduled": "2026-03-05T19:05:00Z",
      "estimated": "2026-03-05T18:59:18Z",
      "actual": "2026-03-05T18:59:18Z",
      "status": "Departed",
      "terminal": null,
      "gate": null
    },
    {
      "flightNumber": "VB9145",
      "airline": "VIV",
      "airlineCode": "VIV",
      "origin": null,
      "originCode": null,
      "destination": "Lic. Adolfo Lopez Mateos Int'l",
      "destinationCode": "TLC",
      "scheduled": "2026-03-05T19:05:00Z",
      "estimated": "2026-03-05T18:52:04Z",
      "actual": "2026-03-05T18:52:04Z",
      "status": "Departed",
      "terminal": null,
      "gate": null
    },
    {
      "flightNumber": "XA-PLJ",
      "airline": "—",
      "airlineCode": "",
      "origin": null,
      "originCode": null,
      "destination": "Unknown",
      "destinationCode": "",
      "scheduled": "2026-03-05T19:08:51Z",
      "estimated": "2026-03-05T18:57:21Z",
      "actual": "2026-03-05T18:57:21Z",
      "status": "Departed",
      "terminal": null,
      "gate": null
    },
    {
      "flightNumber": "DL1860",
      "airline": "DAL",
      "airlineCode": "DAL",
      "origin": null,
      "originCode": null,
      "destination": "Minneapolis/St Paul Intl",
      "destinationCode": "MSP",
      "scheduled": "2026-03-05T19:10:00Z",
      "estimated": "2026-03-05T19:03:17Z",
      "actual": "2026-03-05T19:03:17Z",
      "status": "Departed",
      "terminal": null,
      "gate": null
    },
    {
      "flightNumber": "AA3318",
      "airline": "AAL",
      "airlineCode": "AAL",
      "origin": null,
      "originCode": null,
      "destination": "Dallas-Fort Worth Intl",
      "destinationCode": "DFW",
      "scheduled": "2026-03-05T19:10:00Z",
      "estimated": "2026-03-05T19:10:00Z",
      "status": "Scheduled",
      "terminal": null,
      "gate": null
    },
    {
      "flightNumber": "WS2113",
      "airline": "WJA",
      "airlineCode": "WJA",
      "origin": null,
      "originCode": null,
      "destination": "Edmonton Int'l",
      "destinationCode": "YEG",
      "scheduled": "2026-03-05T19:20:00Z",
      "estimated": "2026-03-05T19:33:07Z",
      "actual": "2026-03-05T19:33:07Z",
      "status": "Departed",
      "terminal": null,
      "gate": null
    },
    {
      "flightNumber": "F82623",
      "airline": "FLE",
      "airlineCode": "FLE",
      "origin": null,
      "originCode": null,
      "destination": "Toronto Pearson Int'l",
      "destinationCode": "YYZ",
      "scheduled": "2026-03-05T19:20:00Z",
      "estimated": "2026-03-05T19:26:08Z",
      "actual": "2026-03-05T19:26:08Z",
      "status": "Departed",
      "terminal": null,
      "gate": null
    },
    {
      "flightNumber": "AM333",
      "airline": "AMX",
      "airlineCode": "AMX",
      "origin": null,
      "originCode": null,
      "destination": "Lic. Benito Juarez Int'l",
      "destinationCode": "MEX",
      "scheduled": "2026-03-05T19:25:00Z",
      "estimated": "2026-03-05T19:28:58Z",
      "actual": "2026-03-05T19:28:58Z",
      "status": "Departed",
      "terminal": null,
      "gate": null
    },
    {
      "flightNumber": "WN515",
      "airline": "SWA",
      "airlineCode": "SWA",
      "origin": null,
      "originCode": null,
      "destination": "Denver Intl",
      "destinationCode": "DEN",
      "scheduled": "2026-03-05T19:25:00Z",
      "estimated": "2026-03-05T19:16:44Z",
      "actual": "2026-03-05T19:16:44Z",
      "status": "Departed",
      "terminal": null,
      "gate": null
    },
    {
      "flightNumber": "AS444",
      "airline": "ASA",
      "airlineCode": "ASA",
      "origin": null,
      "originCode": null,
      "destination": "Los Angeles Intl",
      "destinationCode": "LAX",
      "scheduled": "2026-03-05T19:27:00Z",
      "estimated": "2026-03-05T19:23:12Z",
      "actual": "2026-03-05T19:23:12Z",
      "status": "Departed",
      "terminal": null,
      "gate": null
    },
    {
      "flightNumber": "Y4281",
      "airline": "VOI",
      "airlineCode": "VOI",
      "origin": null,
      "originCode": null,
      "destination": "Lic. Benito Juarez Int'l",
      "destinationCode": "MEX",
      "scheduled": "2026-03-05T19:29:00Z",
      "estimated": "2026-03-05T19:41:33Z",
      "actual": "2026-03-05T19:41:33Z",
      "status": "Departed",
      "terminal": null,
      "gate": null
    },
    {
      "flightNumber": "Y45613",
      "airline": "VOI",
      "airlineCode": "VOI",
      "origin": null,
      "originCode": null,
      "destination": "General Mariano Escobedo Int'l",
      "destinationCode": "MTY",
      "scheduled": "2026-03-05T19:40:00Z",
      "estimated": "2026-03-05T20:51:00Z",
      "status": "Scheduled",
      "terminal": null,
      "gate": null
    },
    {
      "flightNumber": "AS471",
      "airline": "ASA",
      "airlineCode": "ASA",
      "origin": null,
      "originCode": null,
      "destination": "San Diego Intl",
      "destinationCode": "SAN",
      "scheduled": "2026-03-05T19:54:00Z",
      "estimated": "2026-03-05T19:47:43Z",
      "actual": "2026-03-05T19:47:43Z",
      "status": "Departed",
      "terminal": null,
      "gate": null
    },
    {
      "flightNumber": "DL1902",
      "airline": "DAL",
      "airlineCode": "DAL",
      "origin": null,
      "originCode": null,
      "destination": "Detroit Metro Wayne Co",
      "destinationCode": "DTW",
      "scheduled": "2026-03-05T20:05:00Z",
      "estimated": "2026-03-05T19:56:00Z",
      "status": "Scheduled",
      "terminal": null,
      "gate": null
    },
    {
      "flightNumber": "WS2151",
      "airline": "WJA",
      "airlineCode": "WJA",
      "origin": null,
      "originCode": null,
      "destination": "Vancouver Int'l",
      "destinationCode": "YVR",
      "scheduled": "2026-03-05T20:05:00Z",
      "estimated": "2026-03-05T20:05:00Z",
      "status": "Scheduled",
      "terminal": null,
      "gate": null
    },
    {
      "flightNumber": "AA2503",
      "airline": "AAL",
      "airlineCode": "AAL",
      "origin": null,
      "originCode": null,
      "destination": "Chicago O'Hare Intl",
      "destinationCode": "ORD",
      "scheduled": "2026-03-05T20:09:00Z",
      "estimated": "2026-03-05T19:57:00Z",
      "status": "Scheduled",
      "terminal": null,
      "gate": null
    },
    {
      "flightNumber": "UA1717",
      "airline": "UAL",
      "airlineCode": "UAL",
      "origin": null,
      "originCode": null,
      "destination": "Chicago O'Hare Intl",
      "destinationCode": "ORD",
      "scheduled": "2026-03-05T20:10:00Z",
      "estimated": "2026-03-05T20:14:00Z",
      "status": "Scheduled",
      "terminal": null,
      "gate": null
    },
    {
      "flightNumber": "Y43121",
      "airline": "VOI",
      "airlineCode": "VOI",
      "origin": null,
      "originCode": null,
      "destination": "General Abelardo L. Rodriguez Int'l",
      "destinationCode": "TIJ",
      "scheduled": "2026-03-05T20:11:00Z",
      "estimated": "2026-03-05T20:11:00Z",
      "status": "Scheduled",
      "terminal": null,
      "gate": null
    },
    {
      "flightNumber": "AA3044",
      "airline": "AAL",
      "airlineCode": "AAL",
      "origin": null,
      "originCode": null,
      "destination": "Phoenix Sky Harbor Intl",
      "destinationCode": "PHX",
      "scheduled": "2026-03-05T20:20:00Z",
      "estimated": "2026-03-05T20:31:00Z",
      "status": "Scheduled",
      "terminal": null,
      "gate": null
    },
    {
      "flightNumber": "WS2453",
      "airline": "WJA",
      "airlineCode": "WJA",
      "origin": null,
      "originCode": null,
      "destination": "Winnipeg Int'l",
      "destinationCode": "YWG",
      "scheduled": "2026-03-05T20:25:00Z",
      "estimated": "2026-03-05T20:25:00Z",
      "status": "Scheduled",
      "terminal": null,
      "gate": null
    },
    {
      "flightNumber": "WN764",
      "airline": "SWA",
      "airlineCode": "SWA",
      "origin": null,
      "originCode": null,
      "destination": "John Wayne",
      "destinationCode": "SNA",
      "scheduled": "2026-03-05T20:25:00Z",
      "estimated": "2026-03-05T20:30:00Z",
      "status": "Scheduled",
      "terminal": null,
      "gate": null
    },
    {
      "flightNumber": "DL1816",
      "airline": "DAL",
      "airlineCode": "DAL",
      "origin": null,
      "originCode": null,
      "destination": "Hartsfield-Jackson Intl",
      "destinationCode": "ATL",
      "scheduled": "2026-03-05T20:37:00Z",
      "estimated": "2026-03-05T20:27:00Z",
      "status": "Scheduled",
      "terminal": null,
      "gate": null
    },
    {
      "flightNumber": "WS2381",
      "airline": "WJA",
      "airlineCode": "WJA",
      "origin": null,
      "originCode": null,
      "destination": "Regina Int'l",
      "destinationCode": "YQR",
      "scheduled": "2026-03-05T20:45:00Z",
      "estimated": "2026-03-05T20:49:00Z",
      "status": "Scheduled",
      "terminal": null,
      "gate": null
    },
    {
      "flightNumber": "AC1348",
      "airline": "ACA",
      "airlineCode": "ACA",
      "origin": null,
      "originCode": null,
      "destination": "Toronto Pearson Int'l",
      "destinationCode": "YYZ",
      "scheduled": "2026-03-05T20:45:00Z",
      "estimated": "2026-03-05T20:49:00Z",
      "status": "Scheduled",
      "terminal": null,
      "gate": null
    },
    {
      "flightNumber": "UA1243",
      "airline": "UAL",
      "airlineCode": "UAL",
      "origin": null,
      "originCode": null,
      "destination": "San Francisco Int'l",
      "destinationCode": "SFO",
      "scheduled": "2026-03-05T20:47:00Z",
      "estimated": "2026-03-05T21:25:00Z",
      "status": "Scheduled",
      "terminal": null,
      "gate": null
    },
    {
      "flightNumber": "Y4561",
      "airline": "VOI",
      "airlineCode": "VOI",
      "origin": null,
      "originCode": null,
      "destination": "Lic. Adolfo Lopez Mateos Int'l",
      "destinationCode": "TLC",
      "scheduled": "2026-03-05T20:48:00Z",
      "estimated": "2026-03-05T20:48:00Z",
      "status": "Scheduled",
      "terminal": null,
      "gate": null
    },
    {
      "flightNumber": "Y41311",
      "airline": "VOI",
      "airlineCode": "VOI",
      "origin": null,
      "originCode": null,
      "destination": "Don Miguel Hidalgo y Costilla Int'l",
      "destinationCode": "GDL",
      "scheduled": "2026-03-05T20:48:30Z",
      "estimated": "2026-03-05T20:49:00Z",
      "status": "Scheduled",
      "terminal": null,
      "gate": null
    },
    {
      "flightNumber": "VB4341",
      "airline": "VIV",
      "airlineCode": "VIV",
      "origin": null,
      "originCode": null,
      "destination": "General Mariano Escobedo Int'l",
      "destinationCode": "MTY",
      "scheduled": "2026-03-05T20:50:00Z",
      "estimated": "2026-03-05T20:50:00Z",
      "status": "Scheduled",
      "terminal": null,
      "gate": null
    },
    {
      "flightNumber": "N668QS",
      "airline": "—",
      "airlineCode": "",
      "origin": null,
      "originCode": null,
      "destination": "Laredo Intl",
      "destinationCode": "LRD",
      "scheduled": "2026-03-05T20:54:00Z",
      "estimated": "2026-03-05T21:00:00Z",
      "status": "Scheduled",
      "terminal": null,
      "gate": null
    },
    {
      "flightNumber": "AA1215",
      "airline": "AAL",
      "airlineCode": "AAL",
      "origin": null,
      "originCode": null,
      "destination": "Dallas-Fort Worth Intl",
      "destinationCode": "DFW",
      "scheduled": "2026-03-05T21:00:00Z",
      "estimated": "2026-03-05T21:11:00Z",
      "status": "Scheduled",
      "terminal": null,
      "gate": null
    },
    {
      "flightNumber": "WS2251",
      "airline": "WJA",
      "airlineCode": "WJA",
      "origin": null,
      "originCode": null,
      "destination": "Calgary Int'l",
      "destinationCode": "YYC",
      "scheduled": "2026-03-05T21:05:00Z",
      "estimated": "2026-03-05T21:05:00Z",
      "status": "Scheduled",
      "terminal": null,
      "gate": null
    },
    {
      "flightNumber": "AS1350",
      "airline": "ASA",
      "airlineCode": "ASA",
      "origin": null,
      "originCode": null,
      "destination": "San Jose Int'l",
      "destinationCode": "SJC",
      "scheduled": "2026-03-05T21:07:00Z",
      "estimated": "2026-03-05T21:15:00Z",
      "status": "Scheduled",
      "terminal": null,
      "gate": null
    },
    {
      "flightNumber": "VB8033",
      "airline": "VIV",
      "airlineCode": "VIV",
      "origin": null,
      "originCode": null,
      "destination": "Abraham Gonzalez Int'l",
      "destinationCode": "CJS",
      "scheduled": "2026-03-05T21:10:00Z",
      "estimated": "2026-03-05T21:10:00Z",
      "status": "Scheduled",
      "terminal": null,
      "gate": null
    },
    {
      "flightNumber": "UA296",
      "airline": "UAL",
      "airlineCode": "UAL",
      "origin": null,
      "originCode": null,
      "destination": "Denver Intl",
      "destinationCode": "DEN",
      "scheduled": "2026-03-05T21:18:00Z",
      "estimated": "2026-03-05T21:22:00Z",
      "status": "Scheduled",
      "terminal": null,
      "gate": null
    },
    {
      "flightNumber": "DL1817",
      "airline": "DAL",
      "airlineCode": "DAL",
      "origin": null,
      "originCode": null,
      "destination": "Minneapolis/St Paul Intl",
      "destinationCode": "MSP",
      "scheduled": "2026-03-05T21:20:00Z",
      "estimated": "2026-03-05T21:20:00Z",
      "status": "Scheduled",
      "terminal": null,
      "gate": null
    },
    {
      "flightNumber": "AA2278",
      "airline": "AAL",
      "airlineCode": "AAL",
      "origin": null,
      "originCode": null,
      "destination": "Chicago O'Hare Intl",
      "destinationCode": "ORD",
      "scheduled": "2026-03-05T21:20:00Z",
      "estimated": "2026-03-05T21:30:00Z",
      "status": "Scheduled",
      "terminal": null,
      "gate": null
    },
    {
      "flightNumber": "Y47305",
      "airline": "VOI",
      "airlineCode": "VOI",
      "origin": null,
      "originCode": null,
      "destination": "Del Bajio Guanajuato Int'l",
      "destinationCode": "BJX",
      "scheduled": "2026-03-05T21:26:00Z",
      "estimated": "2026-03-05T21:26:00Z",
      "status": "Scheduled",
      "terminal": null,
      "gate": null
    },
    {
      "flightNumber": "F82801",
      "airline": "FLE",
      "airlineCode": "FLE",
      "origin": null,
      "originCode": null,
      "destination": "Vancouver Int'l",
      "destinationCode": "YVR",
      "scheduled": "2026-03-05T21:30:00Z",
      "estimated": "2026-03-05T21:30:00Z",
      "status": "Scheduled",
      "terminal": null,
      "gate": null
    },
    {
      "flightNumber": "WN773",
      "airline": "SWA",
      "airlineCode": "SWA",
      "origin": null,
      "originCode": null,
      "destination": "San Diego Intl",
      "destinationCode": "SAN",
      "scheduled": "2026-03-05T21:30:00Z",
      "estimated": "2026-03-05T21:35:00Z",
      "status": "Scheduled",
      "terminal": null,
      "gate": null
    },
    {
      "flightNumber": "VB7413",
      "airline": "VIV",
      "airlineCode": "VIV",
      "origin": null,
      "originCode": null,
      "destination": "Don Miguel Hidalgo y Costilla Int'l",
      "destinationCode": "GDL",
      "scheduled": "2026-03-05T21:40:00Z",
      "estimated": "2026-03-05T21:40:00Z",
      "status": "Scheduled",
      "terminal": null,
      "gate": null
    },
    {
      "flightNumber": "AM337",
      "airline": "AMX",
      "airlineCode": "AMX",
      "origin": null,
      "originCode": null,
      "destination": "Lic. Benito Juarez Int'l",
      "destinationCode": "MEX",
      "scheduled": "2026-03-05T21:45:00Z",
      "estimated": "2026-03-05T21:45:00Z",
      "status": "Scheduled",
      "terminal": null,
      "gate": null
    },
    {
      "flightNumber": "UA1166",
      "airline": "UAL",
      "airlineCode": "UAL",
      "origin": null,
      "originCode": null,
      "destination": "Houston Bush Int'ctl",
      "destinationCode": "IAH",
      "scheduled": "2026-03-05T21:50:00Z",
      "estimated": "2026-03-05T21:54:00Z",
      "status": "Scheduled",
      "terminal": null,
      "gate": null
    },
    {
      "flightNumber": "Y47507",
      "airline": "VOI",
      "airlineCode": "VOI",
      "origin": null,
      "originCode": null,
      "destination": "Queretaro Intercontinental Airport",
      "destinationCode": "QRO",
      "scheduled": "2026-03-05T22:04:00Z",
      "estimated": "2026-03-05T22:04:00Z",
      "status": "Scheduled",
      "terminal": null,
      "gate": null
    },
    {
      "flightNumber": "AC998",
      "airline": "ACA",
      "airlineCode": "ACA",
      "origin": null,
      "originCode": null,
      "destination": "Montreal-Trudeau",
      "destinationCode": "YUL",
      "scheduled": "2026-03-05T22:05:00Z",
      "estimated": "2026-03-05T22:09:00Z",
      "status": "Scheduled",
      "terminal": null,
      "gate": null
    },
    {
      "flightNumber": "AA3272",
      "airline": "AAL",
      "airlineCode": "AAL",
      "origin": null,
      "originCode": null,
      "destination": "Phoenix Sky Harbor Intl",
      "destinationCode": "PHX",
      "scheduled": "2026-03-05T22:06:00Z",
      "estimated": "2026-03-05T22:16:00Z",
      "status": "Scheduled",
      "terminal": null,
      "gate": null
    },
    {
      "flightNumber": "WS2153",
      "airline": "WJA",
      "airlineCode": "WJA",
      "origin": null,
      "originCode": null,
      "destination": "Vancouver Int'l",
      "destinationCode": "YVR",
      "scheduled": "2026-03-05T22:10:00Z",
      "estimated": "2026-03-05T22:10:00Z",
      "status": "Scheduled",
      "terminal": null,
      "gate": null
    },
    {
      "flightNumber": "AS661",
      "airline": "ASA",
      "airlineCode": "ASA",
      "origin": null,
      "originCode": null,
      "destination": "Seattle-Tacoma Intl",
      "destinationCode": "SEA",
      "scheduled": "2026-03-05T22:10:00Z",
      "estimated": "2026-03-05T22:16:00Z",
      "status": "Scheduled",
      "terminal": null,
      "gate": null
    },
    {
      "flightNumber": "WS2041",
      "airline": "WJA",
      "airlineCode": "WJA",
      "origin": null,
      "originCode": null,
      "destination": "Victoria Int'l",
      "destinationCode": "YYJ",
      "scheduled": "2026-03-05T22:15:00Z",
      "estimated": "2026-03-05T22:15:00Z",
      "status": "Scheduled",
      "terminal": null,
      "gate": null
    },
    {
      "flightNumber": "VB5085",
      "airline": "VIV",
      "airlineCode": "VIV",
      "origin": null,
      "originCode": null,
      "destination": "General Abelardo L. Rodriguez Int'l",
      "destinationCode": "TIJ",
      "scheduled": "2026-03-05T22:20:00Z",
      "estimated": "2026-03-05T22:20:00Z",
      "status": "Scheduled",
      "terminal": null,
      "gate": null
    },
    {
      "flightNumber": "UA2369",
      "airline": "UAL",
      "airlineCode": "UAL",
      "origin": null,
      "originCode": null,
      "destination": "Denver Intl",
      "destinationCode": "DEN",
      "scheduled": "2026-03-05T22:21:00Z",
      "estimated": "2026-03-05T22:21:00Z",
      "status": "Scheduled",
      "terminal": null,
      "gate": null
    },
    {
      "flightNumber": "AS249",
      "airline": "ASA",
      "airlineCode": "ASA",
      "origin": null,
      "originCode": null,
      "destination": "John F Kennedy Intl",
      "destinationCode": "JFK",
      "scheduled": "2026-03-05T22:27:00Z",
      "estimated": "2026-03-05T22:39:00Z",
      "status": "Scheduled",
      "terminal": null,
      "gate": null
    },
    {
      "flightNumber": "WN109",
      "airline": "SWA",
      "airlineCode": "SWA",
      "origin": null,
      "originCode": null,
      "destination": "William P Hobby",
      "destinationCode": "HOU",
      "scheduled": "2026-03-05T22:30:00Z",
      "estimated": "2026-03-05T22:35:00Z",
      "status": "Scheduled",
      "terminal": null,
      "gate": null
    },
    {
      "flightNumber": "5D881",
      "airline": "SLI",
      "airlineCode": "SLI",
      "origin": null,
      "originCode": null,
      "destination": "Mexico City Santa Lucía Airport",
      "destinationCode": "NLU",
      "scheduled": "2026-03-05T22:33:00Z",
      "estimated": "2026-03-05T22:33:00Z",
      "status": "Scheduled",
      "terminal": null,
      "gate": null
    },
    {
      "flightNumber": "SY536",
      "airline": "SCX",
      "airlineCode": "SCX",
      "origin": null,
      "originCode": null,
      "destination": "Minneapolis/St Paul Intl",
      "destinationCode": "MSP",
      "scheduled": "2026-03-05T22:40:00Z",
      "estimated": "2026-03-05T22:40:00Z",
      "status": "Scheduled",
      "terminal": null,
      "gate": null
    },
    {
      "flightNumber": "DL1838",
      "airline": "DAL",
      "airlineCode": "DAL",
      "origin": null,
      "originCode": null,
      "destination": "Salt Lake City Intl",
      "destinationCode": "SLC",
      "scheduled": "2026-03-05T22:45:00Z",
      "estimated": "2026-03-05T22:45:00Z",
      "status": "Scheduled",
      "terminal": null,
      "gate": null
    },
    {
      "flightNumber": "AA1288",
      "airline": "AAL",
      "airlineCode": "AAL",
      "origin": null,
      "originCode": null,
      "destination": "Dallas-Fort Worth Intl",
      "destinationCode": "DFW",
      "scheduled": "2026-03-05T22:45:00Z",
      "estimated": "2026-03-05T22:56:00Z",
      "status": "Scheduled",
      "terminal": null,
      "gate": null
    },
    {
      "flightNumber": "Y43123",
      "airline": "VOI",
      "airlineCode": "VOI",
      "origin": null,
      "originCode": null,
      "destination": "General Abelardo L. Rodriguez Int'l",
      "destinationCode": "TIJ",
      "scheduled": "2026-03-05T22:46:00Z",
      "estimated": "2026-03-05T22:46:00Z",
      "status": "Scheduled",
      "terminal": null,
      "gate": null
    },
    {
      "flightNumber": "UA244",
      "airline": "UAL",
      "airlineCode": "UAL",
      "origin": null,
      "originCode": null,
      "destination": "Los Angeles Intl",
      "destinationCode": "LAX",
      "scheduled": "2026-03-05T22:53:00Z",
      "estimated": "2026-03-05T22:55:00Z",
      "status": "Scheduled",
      "terminal": null,
      "gate": null
    },
    {
      "flightNumber": "AA1881",
      "airline": "AAL",
      "airlineCode": "AAL",
      "origin": null,
      "originCode": null,
      "destination": "Los Angeles Intl",
      "destinationCode": "LAX",
      "scheduled": "2026-03-05T23:01:00Z",
      "estimated": "2026-03-06T00:17:00Z",
      "status": "Scheduled",
      "terminal": null,
      "gate": null
    },
    {
      "flightNumber": "Y41313",
      "airline": "VOI",
      "airlineCode": "VOI",
      "origin": null,
      "originCode": null,
      "destination": "Don Miguel Hidalgo y Costilla Int'l",
      "destinationCode": "GDL",
      "scheduled": "2026-03-05T23:19:30Z",
      "estimated": "2026-03-05T23:20:00Z",
      "status": "Scheduled",
      "terminal": null,
      "gate": null
    },
    {
      "flightNumber": "WS2451",
      "airline": "WJA",
      "airlineCode": "WJA",
      "origin": null,
      "originCode": null,
      "destination": "Winnipeg Int'l",
      "destinationCode": "YWG",
      "scheduled": "2026-03-05T23:20:00Z",
      "estimated": "2026-03-05T23:20:00Z",
      "status": "Scheduled",
      "terminal": null,
      "gate": null
    },
    {
      "flightNumber": "DL1779",
      "airline": "DAL",
      "airlineCode": "DAL",
      "origin": null,
      "originCode": null,
      "destination": "Los Angeles Intl",
      "destinationCode": "LAX",
      "scheduled": "2026-03-05T23:23:00Z",
      "estimated": "2026-03-05T23:23:00Z",
      "status": "Scheduled",
      "terminal": null,
      "gate": null
    },
    {
      "flightNumber": "UA234",
      "airline": "UAL",
      "airlineCode": "UAL",
      "origin": null,
      "originCode": null,
      "destination": "Houston Bush Int'ctl",
      "destinationCode": "IAH",
      "scheduled": "2026-03-05T23:24:00Z",
      "estimated": "2026-03-05T23:24:00Z",
      "status": "Scheduled",
      "terminal": null,
      "gate": null
    },
    {
      "flightNumber": "AS1445",
      "airline": "ASA",
      "airlineCode": "ASA",
      "origin": null,
      "originCode": null,
      "destination": "Portland Intl",
      "destinationCode": "PDX",
      "scheduled": "2026-03-05T23:26:00Z",
      "estimated": "2026-03-05T23:38:00Z",
      "status": "Scheduled",
      "terminal": null,
      "gate": null
    },
    {
      "flightNumber": "WS2241",
      "airline": "WJA",
      "airlineCode": "WJA",
      "origin": null,
      "originCode": null,
      "destination": "Calgary Int'l",
      "destinationCode": "YYC",
      "scheduled": "2026-03-05T23:40:00Z",
      "estimated": "2026-03-05T23:40:00Z",
      "status": "Scheduled",
      "terminal": null,
      "gate": null
    },
    {
      "flightNumber": "WN1299",
      "airline": "SWA",
      "airlineCode": "SWA",
      "origin": null,
      "originCode": null,
      "destination": "Phoenix Sky Harbor Intl",
      "destinationCode": "PHX",
      "scheduled": "2026-03-05T23:45:00Z",
      "estimated": "2026-03-05T23:50:00Z",
      "status": "Scheduled",
      "terminal": null,
      "gate": null
    },
    {
      "flightNumber": "AC971",
      "airline": "ACA",
      "airlineCode": "ACA",
      "origin": null,
      "originCode": null,
      "destination": "Vancouver Int'l",
      "destinationCode": "YVR",
      "scheduled": "2026-03-05T23:50:00Z",
      "estimated": "2026-03-05T23:50:00Z",
      "status": "Scheduled",
      "terminal": null,
      "gate": null
    },
    {
      "flightNumber": "Y45615",
      "airline": "VOI",
      "airlineCode": "VOI",
      "origin": null,
      "originCode": null,
      "destination": "General Mariano Escobedo Int'l",
      "destinationCode": "MTY",
      "scheduled": "2026-03-05T23:55:00Z",
      "estimated": "2026-03-05T23:55:00Z",
      "status": "Scheduled",
      "terminal": null,
      "gate": null
    },
    {
      "flightNumber": "VB1169",
      "airline": "VIV",
      "airlineCode": "VIV",
      "origin": null,
      "originCode": null,
      "destination": "Lic. Benito Juarez Int'l",
      "destinationCode": "MEX",
      "scheduled": "2026-03-05T23:55:00Z",
      "estimated": "2026-03-05T23:55:00Z",
      "status": "Scheduled",
      "terminal": null,
      "gate": null
    },
    {
      "flightNumber": "AS1427",
      "airline": "ASA",
      "airlineCode": "ASA",
      "origin": null,
      "originCode": null,
      "destination": "Seattle-Tacoma Intl",
      "destinationCode": "SEA",
      "scheduled": "2026-03-05T23:55:00Z",
      "estimated": "2026-03-05T23:55:00Z",
      "status": "Scheduled",
      "terminal": null,
      "gate": null
    },
    {
      "flightNumber": "UA705",
      "airline": "UAL",
      "airlineCode": "UAL",
      "origin": null,
      "originCode": null,
      "destination": "San Francisco Int'l",
      "destinationCode": "SFO",
      "scheduled": "2026-03-05T23:56:00Z",
      "estimated": "2026-03-05T23:56:00Z",
      "status": "Scheduled",
      "terminal": null,
      "gate": null
    },
    {
      "flightNumber": "TS107",
      "airline": "TSC",
      "airlineCode": "TSC",
      "origin": null,
      "originCode": null,
      "destination": "Montreal-Trudeau",
      "destinationCode": "YUL",
      "scheduled": "2026-03-06T00:00:00Z",
      "estimated": "2026-03-06T00:00:00Z",
      "status": "Scheduled",
      "terminal": null,
      "gate": null
    },
    {
      "flightNumber": "DL1922",
      "airline": "DAL",
      "airlineCode": "DAL",
      "origin": null,
      "originCode": null,
      "destination": "Seattle-Tacoma Intl",
      "destinationCode": "SEA",
      "scheduled": "2026-03-06T00:00:00Z",
      "estimated": "2026-03-06T00:08:00Z",
      "status": "Scheduled",
      "terminal": null,
      "gate": null
    },
    {
      "flightNumber": "AA3087",
      "airline": "AAL",
      "airlineCode": "AAL",
      "origin": null,
      "originCode": null,
      "destination": "Phoenix Sky Harbor Intl",
      "destinationCode": "PHX",
      "scheduled": "2026-03-06T00:05:00Z",
      "estimated": "2026-03-06T00:05:00Z",
      "status": "Scheduled",
      "terminal": null,
      "gate": null
    },
    {
      "flightNumber": "AS1431",
      "airline": "ASA",
      "airlineCode": "ASA",
      "origin": null,
      "originCode": null,
      "destination": "Los Angeles Intl",
      "destinationCode": "LAX",
      "scheduled": "2026-03-06T01:09:00Z",
      "estimated": "2026-03-06T01:21:00Z",
      "status": "Scheduled",
      "terminal": null,
      "gate": null
    },
    {
      "flightNumber": "F82509",
      "airline": "FLE",
      "airlineCode": "FLE",
      "origin": null,
      "originCode": null,
      "destination": "Calgary Int'l",
      "destinationCode": "YYC",
      "scheduled": "2026-03-06T01:15:00Z",
      "estimated": "2026-03-06T01:15:00Z",
      "status": "Scheduled",
      "terminal": null,
      "gate": null
    },
    {
      "flightNumber": "PD770",
      "airline": "POE",
      "airlineCode": "POE",
      "origin": null,
      "originCode": null,
      "destination": "Hamilton/John C. Munro Int'l",
      "destinationCode": "YHM",
      "scheduled": "2026-03-06T01:25:00Z",
      "estimated": "2026-03-06T01:15:00Z",
      "status": "Scheduled",
      "terminal": null,
      "gate": null
    },
    {
      "flightNumber": "AM341",
      "airline": "AMX",
      "airlineCode": "AMX",
      "origin": null,
      "originCode": null,
      "destination": "Lic. Benito Juarez Int'l",
      "destinationCode": "MEX",
      "scheduled": "2026-03-06T01:44:00Z",
      "estimated": "2026-03-06T01:44:00Z",
      "status": "Scheduled",
      "terminal": null,
      "gate": null
    },
    {
      "flightNumber": "AS690",
      "airline": "ASA",
      "airlineCode": "ASA",
      "origin": null,
      "originCode": null,
      "destination": "San Francisco Int'l",
      "destinationCode": "SFO",
      "scheduled": "2026-03-06T02:09:00Z",
      "estimated": "2026-03-06T02:09:00Z",
      "status": "Scheduled",
      "terminal": null,
      "gate": null
    },
    {
      "flightNumber": "VB7123",
      "airline": "VIV",
      "airlineCode": "VIV",
      "origin": null,
      "originCode": null,
      "destination": "Don Miguel Hidalgo y Costilla Int'l",
      "destinationCode": "GDL",
      "scheduled": "2026-03-06T02:10:00Z",
      "estimated": "2026-03-06T02:20:00Z",
      "status": "Scheduled",
      "terminal": null,
      "gate": null
    },
    {
      "flightNumber": "TS633",
      "airline": "TSC",
      "airlineCode": "TSC",
      "origin": null,
      "originCode": null,
      "destination": "Quebec/Jean Lesage Int'l",
      "destinationCode": "YQB",
      "scheduled": "2026-03-06T02:15:00Z",
      "estimated": "2026-03-06T02:15:00Z",
      "status": "Scheduled",
      "terminal": null,
      "gate": null
    },
    {
      "flightNumber": "F82705",
      "airline": "FLE",
      "airlineCode": "FLE",
      "origin": null,
      "originCode": null,
      "destination": "Edmonton Int'l",
      "destinationCode": "YEG",
      "scheduled": "2026-03-06T02:15:00Z",
      "estimated": "2026-03-06T02:15:00Z",
      "status": "Scheduled",
      "terminal": null,
      "gate": null
    }
  ]
}